Workbook

Sheet Guide
A1: IRB Infrastructure Developers Ltd — Financial Spreading & Ratio Analysis Model
A2: Consolidated, ₹ crore, FY2022–FY2026 actuals with FY2027E–FY2031E projections. Prepared 19 Oct 2026.
A4: TABS
A5: Inputs | B5: Spread of P&L, balance sheet and cash-flow items for 5 years, plus parameters (days, TNW switch, benchmark thresholds).
A6: Ratios | B6: Historical DSCR, TOL/TNW, current ratio, ICR, working capital cycle and supporting credit metrics, with benchmark flags.
A7: Projections | B7: Five-year driver-based projection: P&L, debt schedule, balance sheet, cash flow, ratios and integrity checks.
A8: Sensitivity | B8: Four live grids on FY2027E DSCR, ICR and TOL/TNW (revenue growth, margin, interest rate, additional borrowing).
A10: COLOUR LEGEND
A11: Blue text | B11: Hard-coded input or assumption — safe to overwrite.
A12: Black text | B12: Formula — do not overwrite.
A13: Green text | B13: Link to another sheet.
A14: Yellow fill | B14: Key assumption the user is expected to review (parameters; projection drivers).
A15: Red / green fill | B15: Benchmark breached / met (conditional formatting; thresholds on Inputs rows 7–10).
A17: RATIO DEFINITIONS
A18: DSCR | B18: (PAT – exceptional items + depreciation + finance cost) ÷ (finance cost + prior-year current portion of long-term debt). FY2022 is n.a. (no FY2021 spread).
A19: TOL / TNW | B19: Total outside liabilities ÷ tangible net worth. TNW = net worth (incl. minority) less intangibles × switch (Inputs!B6; default 0 = concession rights treated as tangible). A strict memo line is shown on Ratios.
A20: Current ratio | B20: Total current assets ÷ total current liabilities (current liabilities include current maturities of debt).
A21: ICR | B21: (PBT before exceptional items + finance cost) ÷ finance cost. EBITDA/interest is shown as a memo.
A22: Working capital cycle | B22: Debtor days (receivables ÷ sales) + inventory days – creditor days (both ÷ operating expenditure), on year-end balances.
A24: DATA SOURCES & NOTES
A25: P&L | B25: Consolidated annual results as published by Anand Rathi (anandrathi.com/stocks/irb-infradeveloper/financial-results/200048); FY2026 results announced May 2026.
A26: Balance sheet & cash flow | B26: S&P Global Market Intelligence via StockAnalysis.com (NSE:IRB), published in ₹ million and converted to ₹ crore (÷ 10). Total assets FY2026 = ₹54,054 cr here vs ₹53,998 cr on Screener — vendor classification differs slightly.
A27: Balancing lines | B27: Other current assets, other non-current assets, other current liabilities and other non-current liabilities are derived so that each subtotal ties to the vendor's reported totals. Other non-current liabilities (~₹11,500 cr) sit inside TOL; check their composition in the annual report notes before relying on TOL/TNW.
A28: FY2025 exceptional gain | B28: FY2025 PAT of ₹6,618 cr includes a ₹5,804 cr one-off gain; ratios strip it out (adjusted PAT / PBT).
A29: Projections | B29: Base-case drivers are illustrative, not management guidance or a forecast. Exceptional items are assumed nil; PPE is held flat; new borrowing is an input chosen so cash stays non-negative.
A30: Benchmarks | B30: DSCR ≥ 1.20x, current ratio ≥ 1.00x, TOL/TNW ≤ 3.00x, ICR ≥ 1.50x are placeholder thresholds, not IRB's actual covenants.
A31: Re-use | B31: To analyse another borrower, overwrite the blue cells on Inputs (including the four balancing lines) and the projection drivers; everything else recalculates.

Sheet Inputs
A1: IRB Infrastructure Developers Ltd — Financial Spreading (Consolidated)
A2: ₹ crore, fiscal years ended 31 March. Blue = hard-coded input (overwrite to re-use for another borrower); black = formula.
A4: PARAMETERS & BENCHMARKS
A5: Days in year (for working-capital days) | B5: 365 | G5: Assumption
A6: Deduct intangibles (concession rights) from TNW? 1 = Yes, 0 = No | B6: 0 | G6: Assumption: default 0 because toll/BOT concession rights are the revenue-generating asset. Set 1 for the strict view.
A7: Benchmark: minimum DSCR (x) | B7: 1.2 | G7: Illustrative threshold — replace with sanction/covenant terms
A8: Benchmark: minimum current ratio (x) | B8: 1 | G8: Illustrative threshold — replace with sanction/covenant terms
A9: Benchmark: maximum TOL/TNW (x) | B9: 3 | G9: Illustrative threshold — replace with sanction/covenant terms
A10: Benchmark: minimum ICR (x) | B10: 1.5 | G10: Illustrative threshold — replace with sanction/covenant terms
A13: ₹ crore | B13: FY2022 | C13: FY2023 | D13: FY2024 | E13: FY2025 | F13: FY2026 | G13: Source / note
A14: INCOME STATEMENT
A15: Net sales / revenue from operations | B15: 5803.7 | C15: 6401.64 | D15: 7409 | E15: 7613.47 | F15: 7648.15 | G15: Consolidated results, Anand Rathi (anandrathi.com)
A16: Total operating expenditure | B16: 3006.2 | C16: 3172.61 | D16: 4077.21 | E16: 4007.62 | F16: 3666.33 | G16: Consolidated results, Anand Rathi (anandrathi.com)
A17: EBITDA (PBIDT excl. other income) | B17: =B15-B16 -> 2797.5 | C17: =C15-C16 -> 3229.03 | D17: =D15-D16 -> 3331.79 | E17: =E15-E16 -> 3605.85 | F17: =F15-F16 -> 3981.82
A18: Other income | B18: 551.75 | C18: 301.67 | D18: 792.76 | E18: 418.08 | F18: 205.83 | G18: Consolidated results, Anand Rathi (anandrathi.com)
A19: Finance cost (interest) | B19: 1890.62 | C19: 1514.63 | D19: 1863.32 | E19: 1791.94 | F19: 1755.15 | G19: Consolidated results, Anand Rathi (anandrathi.com)
A20: Exceptional items (gain + / loss –) | B20: 0 | C20: 0 | D20: 0 | E20: 5804.13 | F20: -42.65 | G20: FY25 = ₹5,804 cr one-off gain (non-cash, InvIT-related); FY26 = loss
A21: Depreciation & amortisation | B21: 682.77 | C21: 832.12 | D21: 994.95 | E21: 1037.63 | F21: 1142.04 | G21: Consolidated results, Anand Rathi (anandrathi.com)
A22: Profit before tax | B22: =B17+B18-B19+B20-B21 -> 775.86 | C22: =C17+C18-C19+C20-C21 -> 1183.95 | D22: =D17+D18-D19+D20-D21 -> 1266.28 | E22: =E17+E18-E19+E20-E21 -> 6998.49 | F22: =F17+F18-F19+F20-F21 -> 1247.81
A23: Tax expense | B23: 188.23 | C23: 356.94 | D23: 345.62 | E23: 380.71 | F23: 397.46 | G23: Consolidated results, Anand Rathi (anandrathi.com)
A24: Profit after tax (before minority interest) | B24: =B22-B23 -> 587.63 | C24: =C22-C23 -> 827.01 | D24: =D22-D23 -> 920.66 | E24: =E22-E23 -> 6617.78 | F24: =F22-F23 -> 850.35
A25: Reported PAT (for tie-out) | B25: 587.62 | C25: 827.02 | D25: 920.67 | E25: 6617.79 | F25: 850.36 | G25: Consolidated results, Anand Rathi (anandrathi.com)
A26: Check: computed PAT – reported PAT (rounding only) | B26: =B24-B25 -> 0.01 | C26: =C24-C25 -> -0.01 | D26: =D24-D25 -> -0.01 | E26: =E24-E25 -> -0.01 | F26: =F24-F25 -> -0.01
A28: BALANCE SHEET — ASSETS
A29: Cash & cash equivalents | B29: 52.98 | C29: 300.6 | D29: 232.7 | E29: 1859.5 | F29: 346.3 | G29: S&P Global via StockAnalysis (₹ mn ÷ 10)
A30: Short-term investments / trading securities | B30: 463.5 | C30: 195.7 | D30: 265 | E30: 16.72 | F30: 181.2 | G30: S&P Global via StockAnalysis (₹ mn ÷ 10)
A31: Trade receivables | B31: 1512.9 | C31: 2300.1 | D31: 1317.6 | E31: 994.2 | F31: 1075.5 | G31: S&P Global via StockAnalysis (₹ mn ÷ 10)
A32: Other receivables | B32: 428.2 | C32: 702 | D32: 710.7 | E32: 699.8 | F32: 706.2 | G32: S&P Global via StockAnalysis (₹ mn ÷ 10)
A33: Inventory | B33: 317.5 | C33: 299 | D33: 293.1 | E33: 338.6 | F33: 367 | G33: S&P Global via StockAnalysis (₹ mn ÷ 10)
A34: Prepaid expenses | B34: 46.32 | C34: 16.81 | D34: 4.98 | E34: 4.07 | F34: 9.9 | G34: S&P Global via StockAnalysis (₹ mn ÷ 10)
A35: Other current assets (balancing to reported total) | B35: 2306.1 | C35: 3150.89 | D35: 2015.32 | E35: 1995.81 | F35: 1995.6 | G35: Derived: reported total current assets less the lines above
A36: Total current assets | B36: =SUM(B29:B35) -> 5127.5 | C36: =SUM(C29:C35) -> 6965.1 | D36: =SUM(D29:D35) -> 4839.4 | E36: =SUM(E29:E35) -> 5908.7 | F36: =SUM(F29:F35) -> 4681.7
A37: Property, plant & equipment | B37: 984.2 | C37: 950 | D37: 922 | E37: 986.3 | F37: 946.1 | G37: S&P Global via StockAnalysis (₹ mn ÷ 10)
A38: Intangibles incl. goodwill (concession rights) | B38: 26349.4 | C38: 25537.6 | D38: 24599.4 | E38: 23630.4 | F38: 22953.8 | G38: S&P Global via StockAnalysis (₹ mn ÷ 10); other intangibles + goodwill
A39: Long-term investments | B39: 4440.7 | C39: 4945.2 | D39: 9377 | E39: 17080.6 | F39: 19147 | G39: S&P Global via StockAnalysis (₹ mn ÷ 10)
A40: Other non-current assets (balancing to reported total) | B40: 5664.8 | C40: 4368.3 | D40: 5182.5 | E40: 6290 | F40: 6325 | G40: Derived: reported total assets less lines above
A41: Total assets | B41: =B36+B37+B38+B39+B40 -> 42566.6 | C41: =C36+C37+C38+C39+C40 -> 42766.2 | D41: =D36+D37+D38+D39+D40 -> 44920.3 | E41: =E36+E37+E38+E39+E40 -> 53896 | F41: =F36+F37+F38+F39+F40 -> 54053.6
A43: BALANCE SHEET — LIABILITIES & EQUITY
A44: Trade payables | B44: 381.7 | C44: 502.2 | D44: 675.7 | E44: 521.8 | F44: 256.8 | G44: S&P Global via StockAnalysis (₹ mn ÷ 10)
A45: Accrued expenses | B45: 83.35 | C45: 151.3 | D45: 306.4 | E45: 181.5 | F45: 170.1 | G45: S&P Global via StockAnalysis (₹ mn ÷ 10)
A46: Short-term borrowings | B46: 583.3 | C46: 1339.1 | D46: 589.1 | E46: 431.9 | F46: 536.1 | G46: S&P Global via StockAnalysis (₹ mn ÷ 10)
A47: Current portion of long-term debt & leases | B47: 636.49 | C47: 1156.86 | D47: 1209.99 | E47: 1453.42 | F47: 1699.18 | G47: S&P Global via StockAnalysis (₹ mn ÷ 10); incl. current lease liabilities
A48: Other current liabilities (balancing to reported total) | B48: 1192.56 | C48: 1155.04 | D48: 1128.11 | E48: 1157.58 | F48: 1117.42 | G48: Derived: reported total current liabilities less lines above (incl. taxes payable)
A49: Total current liabilities | B49: =SUM(B44:B48) -> 2877.4 | C49: =SUM(C44:C48) -> 4304.5 | D49: =SUM(D44:D48) -> 3909.3 | E49: =SUM(E44:E48) -> 3746.2 | F49: =SUM(F44:F48) -> 3779.6
A50: Long-term debt & leases | B50: 15483.21 | C50: 14252.25 | D50: 16854.3 | E50: 18713.98 | F50: 17791.78 | G50: S&P Global via StockAnalysis (₹ mn ÷ 10); incl. long-term lease liabilities
A51: Other non-current liabilities (balancing to reported total) | B51: 11640.39 | C51: 10830.55 | D51: 10412.2 | E51: 11609.22 | F51: 11533.42 | G51: Derived: reported total liabilities less CL and LT debt. Check composition in annual report notes
A52: Total outside liabilities | B52: =B49+B50+B51 -> 30001 | C52: =C49+C50+C51 -> 29387.3 | D52: =D49+D50+D51 -> 31175.8 | E52: =E49+E50+E51 -> 34069.4 | F52: =F49+F50+F51 -> 33104.8
A53: Share capital | B53: 603.9 | C53: 603.9 | D53: 603.9 | E53: 603.9 | F53: 603.9 | G53: S&P Global via StockAnalysis (₹ mn ÷ 10)
A54: Reserves & other equity incl. minority interest | B54: 11961.7 | C54: 12775 | D54: 13140.6 | E54: 19222.7 | F54: 20344.9 | G54: Derived: total equity less share capital
A55: Total equity (net worth incl. minority interest) | B55: =B53+B54 -> 12565.6 | C55: =C53+C54 -> 13378.9 | D55: =D53+D54 -> 13744.5 | E55: =E53+E54 -> 19826.6 | F55: =F53+F54 -> 20948.8
A56: Total liabilities & equity | B56: =B52+B55 -> 42566.6 | C56: =C52+C55 -> 42766.2 | D56: =D52+D55 -> 44920.3 | E56: =E52+E55 -> 53896 | F56: =F52+F55 -> 54053.6
A57: Check: total assets – total liabilities & equity | B57: =B41-B56 -> 0 | C57: =C41-C56 -> 0 | D57: =D41-D56 -> 0 | E57: =E41-E56 -> 0 | F57: =F41-F56 -> 0
A59: DEBT
A60: Total debt (short-term + current portion + long-term) | B60: =B46+B47+B50 -> 16703 | C60: =C46+C47+C50 -> 16748.21 | D60: =D46+D47+D50 -> 18653.39 | E60: =E46+E47+E50 -> 20599.3 | F60: =F46+F47+F50 -> 20027.06
A61: Net debt (total debt – cash – short-term investments) | B61: =B60-B29-B30 -> 16186.52 | C61: =C60-C29-C30 -> 16251.91 | D61: =D60-D29-D30 -> 18155.69 | E61: =E60-E29-E30 -> 18723.08 | F61: =F60-F29-F30 -> 19499.56
A63: CASH FLOW ITEMS
A64: Cash flow from operations (as reported by S&P; interest shown in financing) | B64: 364.1 | C64: 1764.1 | D64: 4053.8 | E64: 1971.2 | F64: 2098 | G64: S&P Global via StockAnalysis cash flow statement
A65: Capital expenditure (PPE) | B65: 247.3 | C65: 49.49 | D65: 29.11 | E65: 112.6 | F65: 64.2 | G65: S&P Global via StockAnalysis
A66: Purchase of intangibles (concession capex) | B66: 1142.3 | C66: 381.4 | D66: 209.9 | E66: 86.03 | F66: 667.9 | G66: S&P Global via StockAnalysis
A67: Dividends paid | B67: 0 | C67: 75.49 | D67: 166.1 | E67: 241.6 | F67: 126.8 | G67: S&P Global via StockAnalysis
A68: Cash interest paid | B68: 1660.7 | C68: 1227.9 | D68: 1659.1 | E68: 1398.4 | F68: 1339.6 | G68: S&P Global via StockAnalysis
A69: Long-term debt repaid | B69: 3290.7 | C69: 1618.7 | D69: 4092.7 | E69: 1219.5 | F69: 1443.4 | G69: S&P Global via StockAnalysis
A70: Net change in cash | B70: -600.8 | C70: 253.3 | D70: -67.89 | E70: 1626.9 | F70: -1513.2 | G70: S&P Global via StockAnalysis
A72: To re-use for another borrower: overwrite the blue cells (and the balancing lines) with the new company's spread; all other tabs recalculate.

Sheet Ratios
A1: IRB Infrastructure Developers Ltd — Ratio Analysis (Historical)
A2: All figures link to the Inputs tab. Green = link to another sheet, black = calculation. Ratios in x unless stated.
A4: ₹ crore / ratio | B4: FY2022 | C4: FY2023 | D4: FY2024 | E4: FY2025 | F4: FY2026 | G4: Definition
A5: A. DEBT SERVICE COVERAGE (DSCR)
A6: Profit after tax | B6: =Inputs!B24 -> 587.63 | C6: =Inputs!C24 -> 827.01 | D6: =Inputs!D24 -> 920.66 | E6: =Inputs!E24 -> 6617.78 | F6: =Inputs!F24 -> 850.35
A7: Less: exceptional items (non-recurring) | B7: =Inputs!B20 -> 0 | C7: =Inputs!C20 -> 0 | D7: =Inputs!D20 -> 0 | E7: =Inputs!E20 -> 5804.13 | F7: =Inputs!F20 -> -42.65
A8: Adjusted PAT | B8: =B6-B7 -> 587.63 | C8: =C6-C7 -> 827.01 | D8: =D6-D7 -> 920.66 | E8: =E6-E7 -> 813.65 | F8: =F6-F7 -> 893
A9: Add: depreciation & amortisation | B9: =Inputs!B21 -> 682.77 | C9: =Inputs!C21 -> 832.12 | D9: =Inputs!D21 -> 994.95 | E9: =Inputs!E21 -> 1037.63 | F9: =Inputs!F21 -> 1142.04
A10: Add: finance cost | B10: =Inputs!B19 -> 1890.62 | C10: =Inputs!C19 -> 1514.63 | D10: =Inputs!D19 -> 1863.32 | E10: =Inputs!E19 -> 1791.94 | F10: =Inputs!F19 -> 1755.15
A11: Cash accruals available for debt service | B11: =B8+B9+B10 -> 3161.02 | C11: =C8+C9+C10 -> 3173.76 | D11: =D8+D9+D10 -> 3778.93 | E11: =E8+E9+E10 -> 3643.22 | F11: =F8+F9+F10 -> 3790.19 | G11: (PAT – exceptional items) + depreciation + finance cost
A12: Scheduled principal (prior-year current portion of LT debt) | B12: n.a. | C12: =Inputs!B47 -> 636.49 | D12: =Inputs!C47 -> 1156.86 | E12: =Inputs!D47 -> 1209.99 | F12: =Inputs!E47 -> 1453.42 | G12: Current maturities of LT debt at the start of the year (FY22 n.a. — FY21 balance sheet not spread)
A13: Debt service (interest + scheduled principal) | B13: n.a. | C13: =C10+C12 -> 2151.12 | D13: =D10+D12 -> 3020.18 | E13: =E10+E12 -> 3001.93 | F13: =F10+F12 -> 3208.57
A14: DSCR (x) | B14: n.a. | C14: =IF(C13>0,C11/C13,"n.a.") -> 1.4753989 | D14: =IF(D13>0,D11/D13,"n.a.") -> 1.2512267 | E14: =IF(E13>0,E11/E13,"n.a.") -> 1.2136259 | F14: =IF(F13>0,F11/F13,"n.a.") -> 1.1812708 | G14: Cash accruals ÷ (interest + scheduled principal)
A15: Memo: reported cash flow from operations | B15: =Inputs!B64 -> 364.1 | C15: =Inputs!C64 -> 1764.1 | D15: =Inputs!D64 -> 4053.8 | E15: =Inputs!E64 -> 1971.2 | F15: =Inputs!F64 -> 2098
A16: Memo: cash interest paid + LT debt repaid | B16: =Inputs!B68+Inputs!B69 -> 4951.4 | C16: =Inputs!C68+Inputs!C69 -> 2846.6 | D16: =Inputs!D68+Inputs!D69 -> 5751.8 | E16: =Inputs!E68+Inputs!E69 -> 2617.9 | F16: =Inputs!F68+Inputs!F69 -> 2783
A17: Memo: cash-based DSCR (x) | B17: =IF(B16>0,B15/B16,"n.a.") -> 0.073534758 | C17: =IF(C16>0,C15/C16,"n.a.") -> 0.61972177 | D17: =IF(D16>0,D15/D16,"n.a.") -> 0.70478807 | E17: =IF(E16>0,E15/E16,"n.a.") -> 0.75296994 | F17: =IF(F16>0,F15/F16,"n.a.") -> 0.75386274 | G17: Reported CFO ÷ (cash interest + LT debt repaid). CFO is shown before interest in the S&P presentation
A19: B. TOL / TNW
A20: Total outside liabilities (TOL) | B20: =Inputs!B52 -> 30001 | C20: =Inputs!C52 -> 29387.3 | D20: =Inputs!D52 -> 31175.8 | E20: =Inputs!E52 -> 34069.4 | F20: =Inputs!F52 -> 33104.8
A21: Net worth (incl. minority interest) | B21: =Inputs!B55 -> 12565.6 | C21: =Inputs!C55 -> 13378.9 | D21: =Inputs!D55 -> 13744.5 | E21: =Inputs!E55 -> 19826.6 | F21: =Inputs!F55 -> 20948.8
A22: Less: intangibles deducted (per switch on Inputs) | B22: =Inputs!B38*Inputs!$B$6 -> 0 | C22: =Inputs!C38*Inputs!$B$6 -> 0 | D22: =Inputs!D38*Inputs!$B$6 -> 0 | E22: =Inputs!E38*Inputs!$B$6 -> 0 | F22: =Inputs!F38*Inputs!$B$6 -> 0
A23: Tangible net worth (TNW) | B23: =B21-B22 -> 12565.6 | C23: =C21-C22 -> 13378.9 | D23: =D21-D22 -> 13744.5 | E23: =E21-E22 -> 19826.6 | F23: =F21-F22 -> 20948.8
A24: TOL / TNW (x) | B24: =IF(B23>0,B20/B23,"n.m.") -> 2.3875501 | C24: =IF(C23>0,C20/C23,"n.m.") -> 2.1965408 | D24: =IF(D23>0,D20/D23,"n.m.") -> 2.2682382 | E24: =IF(E23>0,E20/E23,"n.m.") -> 1.7183683 | F24: =IF(F23>0,F20/F23,"n.m.") -> 1.5802719 | G24: Total outside liabilities ÷ tangible net worth; "n.m." where TNW ≤ 0
A25: Memo: TNW with all intangibles deducted | B25: =B21-Inputs!B38 -> -13783.8 | C25: =C21-Inputs!C38 -> -12158.7 | D25: =D21-Inputs!D38 -> -10854.9 | E25: =E21-Inputs!E38 -> -3803.8 | F25: =F21-Inputs!F38 -> -2005
A26: Memo: TOL / TNW — strict basis (x) | B26: =IF(B25>0,B20/B25,"n.m.") -> n.m. | C26: =IF(C25>0,C20/C25,"n.m.") -> n.m. | D26: =IF(D25>0,D20/D25,"n.m.") -> n.m. | E26: =IF(E25>0,E20/E25,"n.m.") -> n.m. | F26: =IF(F25>0,F20/F25,"n.m.") -> n.m.
A27: Memo: total debt / net worth (x) | B27: =Inputs!B60/B21 -> 1.329264 | C27: =Inputs!C60/C21 -> 1.2518376 | D27: =Inputs!D60/D21 -> 1.357153 | E27: =Inputs!E60/E21 -> 1.0389729 | F27: =Inputs!F60/F21 -> 0.95600034
A29: C. LIQUIDITY
A30: Total current assets | B30: =Inputs!B36 -> 5127.5 | C30: =Inputs!C36 -> 6965.1 | D30: =Inputs!D36 -> 4839.4 | E30: =Inputs!E36 -> 5908.7 | F30: =Inputs!F36 -> 4681.7
A31: Total current liabilities | B31: =Inputs!B49 -> 2877.4 | C31: =Inputs!C49 -> 4304.5 | D31: =Inputs!D49 -> 3909.3 | E31: =Inputs!E49 -> 3746.2 | F31: =Inputs!F49 -> 3779.6
A32: Current ratio (x) | B32: =B30/B31 -> 1.7819907 | C32: =C30/C31 -> 1.6180973 | D32: =D30/D31 -> 1.2379198 | E32: =E30/E31 -> 1.5772516 | F32: =F30/F31 -> 1.2386761 | G32: Current assets ÷ current liabilities
A33: Net working capital | B33: =B30-B31 -> 2250.1 | C33: =C30-C31 -> 2660.6 | D33: =D30-D31 -> 930.1 | E33: =E30-E31 -> 2162.5 | F33: =F30-F31 -> 902.1
A35: D. INTEREST COVERAGE (ICR)
A36: Profit before tax | B36: =Inputs!B22 -> 775.86 | C36: =Inputs!C22 -> 1183.95 | D36: =Inputs!D22 -> 1266.28 | E36: =Inputs!E22 -> 6998.49 | F36: =Inputs!F22 -> 1247.81
A37: PBT before exceptional items | B37: =B36-Inputs!B20 -> 775.86 | C37: =C36-Inputs!C20 -> 1183.95 | D37: =D36-Inputs!D20 -> 1266.28 | E37: =E36-Inputs!E20 -> 1194.36 | F37: =F36-Inputs!F20 -> 1290.46
A38: PBIT before exceptional items (PBT + interest) | B38: =B37+B10 -> 2666.48 | C38: =C37+C10 -> 2698.58 | D38: =D37+D10 -> 3129.6 | E38: =E37+E10 -> 2986.3 | F38: =F37+F10 -> 3045.61
A39: ICR (x) | B39: =B38/B10 -> 1.4103733 | C39: =C38/C10 -> 1.7816761 | D39: =D38/D10 -> 1.6795827 | E39: =E38/E10 -> 1.6665179 | F39: =F38/F10 -> 1.735242 | G39: (PBT before exceptional items + interest) ÷ interest
A40: EBITDA | B40: =Inputs!B17 -> 2797.5 | C40: =Inputs!C17 -> 3229.03 | D40: =Inputs!D17 -> 3331.79 | E40: =Inputs!E17 -> 3605.85 | F40: =Inputs!F17 -> 3981.82
A41: Memo: EBITDA / interest (x) | B41: =B40/B10 -> 1.4796733 | C41: =C40/C10 -> 2.1318936 | D41: =D40/D10 -> 1.7880933 | E41: =E40/E10 -> 2.0122605 | F41: =F40/F10 -> 2.2686494
A43: E. WORKING CAPITAL CYCLE (days, year-end balances)
A44: Net sales | B44: =Inputs!B15 -> 5803.7 | C44: =Inputs!C15 -> 6401.64 | D44: =Inputs!D15 -> 7409 | E44: =Inputs!E15 -> 7613.47 | F44: =Inputs!F15 -> 7648.15
A45: Operating expenditure | B45: =Inputs!B16 -> 3006.2 | C45: =Inputs!C16 -> 3172.61 | D45: =Inputs!D16 -> 4077.21 | E45: =Inputs!E16 -> 4007.62 | F45: =Inputs!F16 -> 3666.33
A46: Trade receivables | B46: =Inputs!B31 -> 1512.9 | C46: =Inputs!C31 -> 2300.1 | D46: =Inputs!D31 -> 1317.6 | E46: =Inputs!E31 -> 994.2 | F46: =Inputs!F31 -> 1075.5
A47: Inventory | B47: =Inputs!B33 -> 317.5 | C47: =Inputs!C33 -> 299 | D47: =Inputs!D33 -> 293.1 | E47: =Inputs!E33 -> 338.6 | F47: =Inputs!F33 -> 367
A48: Trade payables | B48: =Inputs!B44 -> 381.7 | C48: =Inputs!C44 -> 502.2 | D48: =Inputs!D44 -> 675.7 | E48: =Inputs!E44 -> 521.8 | F48: =Inputs!F44 -> 256.8
A49: Debtor days | B49: =B46/B44*Inputs!$B$5 -> 95.147664 | C49: =C46/C44*Inputs!$B$5 -> 131.14397 | D49: =D46/D44*Inputs!$B$5 -> 64.910784 | E49: =E46/E44*Inputs!$B$5 -> 47.663286 | F49: =F46/F44*Inputs!$B$5 -> 51.327118 | G49: Trade receivables ÷ net sales × days in year
A50: Inventory days | B50: =B47/B45*Inputs!$B$5 -> 38.549498 | C50: =C47/C45*Inputs!$B$5 -> 34.399122 | D50: =D47/D45*Inputs!$B$5 -> 26.238899 | E50: =E47/E45*Inputs!$B$5 -> 30.838503 | F50: =F47/F45*Inputs!$B$5 -> 36.536537
A51: Creditor days | B51: =B48/B45*Inputs!$B$5 -> 46.344388 | C51: =C48/C45*Inputs!$B$5 -> 57.77672 | D51: =D48/D45*Inputs!$B$5 -> 60.490016 | E51: =E48/E45*Inputs!$B$5 -> 47.523717 | F51: =F48/F45*Inputs!$B$5 -> 25.56562
A52: Working capital cycle (days) | B52: =B49+B50-B51 -> 87.352774 | C52: =C49+C50-C51 -> 107.76637 | D52: =D49+D50-D51 -> 30.659666 | E52: =E49+E50-E51 -> 30.978072 | F52: =F49+F50-F51 -> 62.298035 | G52: Debtor days + inventory days – creditor days; inventory/creditor days on operating expenditure
A54: F. OTHER CREDIT METRICS
A55: Total debt | B55: =Inputs!B60 -> 16703 | C55: =Inputs!C60 -> 16748.21 | D55: =Inputs!D60 -> 18653.39 | E55: =Inputs!E60 -> 20599.3 | F55: =Inputs!F60 -> 20027.06
A56: Total debt / EBITDA (x) | B56: =B55/B40 -> 5.9706881 | C56: =C55/C40 -> 5.186762 | D56: =D55/D40 -> 5.5986092 | E56: =E55/E40 -> 5.7127446 | F56: =F55/F40 -> 5.0296246
A57: Net debt / EBITDA (x) | B57: =Inputs!B61/B40 -> 5.7860661 | C57: =Inputs!C61/C40 -> 5.0330626 | D57: =Inputs!D61/D40 -> 5.44923 | E57: =Inputs!E61/E40 -> 5.1924179 | F57: =Inputs!F61/F40 -> 4.8971475
A58: Revenue growth | B58: n.a. | C58: =C44/B44-1 -> 0.10302738 | D58: =D44/C44-1 -> 0.15735968 | E58: =E44/D44-1 -> 0.027597517 | F58: =F44/E44-1 -> 0.0045550846
A59: EBITDA margin | B59: =B40/B44 -> 0.48202009 | C59: =C40/C44 -> 0.50440668 | D59: =D40/D44 -> 0.44969497 | E59: =E40/E44 -> 0.47361453 | F59: =F40/F44 -> 0.52062525
A60: PAT margin (before exceptional items) | B60: =B8/B44 -> 0.10125093 | C60: =C8/C44 -> 0.12918721 | D60: =D8/D44 -> 0.12426238 | E60: =E8/E44 -> 0.1068698 | F60: =F8/F44 -> 0.11676026
A62: G. BENCHMARK CHECK (thresholds on Inputs tab)
A63: DSCR | B63: =IF(ISNUMBER(B14),IF(B14>=Inputs!$B$7,"OK","BREACH"),"n.a.") -> n.a. | C63: =IF(ISNUMBER(C14),IF(C14>=Inputs!$B$7,"OK","BREACH"),"n.a.") -> OK | D63: =IF(ISNUMBER(D14),IF(D14>=Inputs!$B$7,"OK","BREACH"),"n.a.") -> OK | E63: =IF(ISNUMBER(E14),IF(E14>=Inputs!$B$7,"OK","BREACH"),"n.a.") -> OK | F63: =IF(ISNUMBER(F14),IF(F14>=Inputs!$B$7,"OK","BREACH"),"n.a.") -> BREACH
A64: Current ratio | B64: =IF(ISNUMBER(B32),IF(B32>=Inputs!$B$8,"OK","BREACH"),"n.a.") -> OK | C64: =IF(ISNUMBER(C32),IF(C32>=Inputs!$B$8,"OK","BREACH"),"n.a.") -> OK | D64: =IF(ISNUMBER(D32),IF(D32>=Inputs!$B$8,"OK","BREACH"),"n.a.") -> OK | E64: =IF(ISNUMBER(E32),IF(E32>=Inputs!$B$8,"OK","BREACH"),"n.a.") -> OK | F64: =IF(ISNUMBER(F32),IF(F32>=Inputs!$B$8,"OK","BREACH"),"n.a.") -> OK
A65: TOL / TNW | B65: =IF(ISNUMBER(B24),IF(B24<=Inputs!$B$9,"OK","BREACH"),"n.a.") -> OK | C65: =IF(ISNUMBER(C24),IF(C24<=Inputs!$B$9,"OK","BREACH"),"n.a.") -> OK | D65: =IF(ISNUMBER(D24),IF(D24<=Inputs!$B$9,"OK","BREACH"),"n.a.") -> OK | E65: =IF(ISNUMBER(E24),IF(E24<=Inputs!$B$9,"OK","BREACH"),"n.a.") -> OK | F65: =IF(ISNUMBER(F24),IF(F24<=Inputs!$B$9,"OK","BREACH"),"n.a.") -> OK
A66: ICR | B66: =IF(ISNUMBER(B39),IF(B39>=Inputs!$B$10,"OK","BREACH"),"n.a.") -> BREACH | C66: =IF(ISNUMBER(C39),IF(C39>=Inputs!$B$10,"OK","BREACH"),"n.a.") -> OK | D66: =IF(ISNUMBER(D39),IF(D39>=Inputs!$B$10,"OK","BREACH"),"n.a.") -> OK | E66: =IF(ISNUMBER(E39),IF(E39>=Inputs!$B$10,"OK","BREACH"),"n.a.") -> OK | F66: =IF(ISNUMBER(F39),IF(F39>=Inputs!$B$10,"OK","BREACH"),"n.a.") -> OK

Sheet Projections
A1: IRB Infrastructure Developers Ltd — Projections FY2027E–FY2031E
A2: ₹ crore. Blue = editable assumption (illustrative base case — replace with management / rating-agency case). Actual columns show historical equivalents of each driver for reference.
B4: Actual | C4: Actual | D4: Actual | E4: Actual | F4: Actual | G4: Projected | H4: Projected | I4: Projected | J4: Projected | K4: Projected
A5: ₹ crore | B5: FY2022 | C5: FY2023 | D5: FY2024 | E5: FY2025 | F5: FY2026 | G5: FY2027E | H5: FY2028E | I5: FY2029E | J5: FY2030E | K5: FY2031E | L5: Assumption / note
A6: KEY ASSUMPTIONS
A7: Revenue growth | C7: =C27/B27-1 -> 0.10302738 | D7: =D27/C27-1 -> 0.15735968 | E7: =E27/D27-1 -> 0.027597517 | F7: =F27/E27-1 -> 0.0045550846 | G7: 0.08 | H7: 0.08 | I7: 0.07 | J7: 0.07 | K7: 0.06 | L7: Illustrative: toll growth offset by lower construction revenue (FY26 reported +0.5%)
A8: EBITDA margin | B8: =B29/B27 -> 0.48202009 | C8: =C29/C27 -> 0.50440668 | D8: =D29/D27 -> 0.44969497 | E8: =E29/E27 -> 0.47361453 | F8: =F29/F27 -> 0.52062525 | G8: 0.52 | H8: 0.52 | I8: 0.52 | J8: 0.52 | K8: 0.52 | L8: Held at ~FY26 level (52.1%)
A9: Other income (% of revenue) | B9: =B30/B27 -> 0.095068663 | C9: =C30/C27 -> 0.047123862 | D9: =D30/D27 -> 0.1069996 | E9: =E30/E27 -> 0.0549132 | F9: =F30/F27 -> 0.026912391 | G9: 0.027 | H9: 0.027 | I9: 0.027 | J9: 0.027 | K9: 0.027 | L9: Held at ~FY26 level (2.7%)
A10: Depreciation & amortisation (% of opening net block) | C10: =C33/(B51+B52) -> 0.030443118 | D10: =D33/(C51+C52) -> 0.03756286 | E10: =E33/(D51+D52) -> 0.040657252 | F10: =F33/(E51+E52) -> 0.046392896 | G10: 0.046 | H10: 0.046 | I10: 0.046 | J10: 0.046 | K10: 0.046 | L10: FY26 = 4.6% of opening PPE + intangibles
A11: Interest rate on average total debt | C11: =C31/AVERAGE(B43,C43) -> 0.090557561 | D11: =D31/AVERAGE(C43,D43) -> 0.10526756 | E11: =E31/AVERAGE(D43,E43) -> 0.091302787 | F11: =F31/AVERAGE(E43,F43) -> 0.086404492 | G11: 0.086 | H11: 0.086 | I11: 0.086 | J11: 0.086 | K11: 0.086 | L11: FY26 = 8.6% on average total debt
A12: Tax rate (on PBT) | B12: =IF(B34-B32>0,B35/(B34-B32),0) -> 0.2426082 | C12: =IF(C34-C32>0,C35/(C34-C32),0) -> 0.30148233 | D12: =IF(D34-D32>0,D35/(D34-D32),0) -> 0.27294121 | E12: =IF(E34-E32>0,E35/(E34-E32),0) -> 0.31875649 | F12: =IF(F34-F32>0,F35/(F34-F32),0) -> 0.3079987 | G12: 0.3 | H12: 0.3 | I12: 0.3 | J12: 0.3 | K12: 0.3 | L12: Effective rate on PBT before exceptional items: FY24 27%, FY26 32%
A13: Capex — PPE (₹ cr) | B13: =Inputs!B65 -> 247.3 | C13: =Inputs!C65 -> 49.49 | D13: =Inputs!D65 -> 29.11 | E13: =Inputs!E65 -> 112.6 | F13: =Inputs!F65 -> 64.2 | G13: 80 | H13: 80 | I13: 80 | J13: 80 | K13: 80 | L13: PPE assumed flat: capex equals PPE depreciation
A14: Capex — concession assets / intangibles (₹ cr) | B14: =Inputs!B66 -> 1142.3 | C14: =Inputs!C66 -> 381.4 | D14: =Inputs!D66 -> 209.9 | E14: =Inputs!E66 -> 86.03 | F14: =Inputs!F66 -> 667.9 | G14: 700 | H14: 700 | I14: 700 | J14: 700 | K14: 700 | L14: FY26 = ₹668 cr; excludes any large new-project pipeline
A15: Net investment in long-term investments / InvIT (₹ cr) | G15: 0 | H15: 0 | I15: 0 | J15: 0 | K15: 0 | L15: Set > 0 to model equity into new projects / InvIT units
A16: New long-term borrowing (₹ cr) | G16: 500 | H16: 500 | I16: 500 | J16: 500 | K16: 500 | L16: Refinancing / drawdown; tune so cash stays ≥ 0 (see checks). FY26 repaid ₹1,443 cr and drew ₹208 cr
A17: Change in short-term borrowings (₹ cr) | G17: 0 | H17: 0 | I17: 0 | J17: 0 | K17: 0
A18: Current portion as % of closing long-term debt | B18: =B59/(B59+B61) -> 0.039485226 | C18: =C59/(C59+C61) -> 0.075076367 | D18: =D59/(D59+D61) -> 0.066982428 | E18: =E59/(E59+E61) -> 0.072067793 | F18: =F59/(F59+F61) -> 0.087177851 | G18: 0.09 | H18: 0.09 | I18: 0.09 | J18: 0.09 | K18: 0.09 | L18: FY26 = 8.7%, FY25 = 7.2%
A19: Dividend payout (% of PAT) | B19: =IF(B36>0,Inputs!B67/B36,0) -> 0 | C19: =IF(C36>0,Inputs!C67/C36,0) -> 0.091280637 | D19: =IF(D36>0,Inputs!D67/D36,0) -> 0.18041405 | E19: =IF(E36>0,Inputs!E67/E36,0) -> 0.036507711 | F19: =IF(F36>0,Inputs!F67/F36,0) -> 0.14911507 | G19: 0.15 | H19: 0.15 | I19: 0.15 | J19: 0.15 | K19: 0.15 | L19: FY26 dividends ₹127 cr = 15% of PAT
A20: Debtor days | B20: =B92 -> 95.147664 | C20: =C92 -> 131.14397 | D20: =D92 -> 64.910784 | E20: =E92 -> 47.663286 | F20: =F92 -> 51.327118 | G20: 51 | H20: 51 | I20: 51 | J20: 51 | K20: 51
A21: Inventory days | B21: =B93 -> 38.549498 | C21: =C93 -> 34.399122 | D21: =D93 -> 26.238899 | E21: =E93 -> 30.838503 | F21: =F93 -> 36.536537 | G21: 36.5 | H21: 36.5 | I21: 36.5 | J21: 36.5 | K21: 36.5
A22: Creditor days | B22: =B94 -> 46.344388 | C22: =C94 -> 57.77672 | D22: =D94 -> 60.490016 | E22: =E94 -> 47.523717 | F22: =F94 -> 25.56562 | G22: 25.6 | H22: 25.6 | I22: 25.6 | J22: 25.6 | K22: 25.6
A23: Other current assets (% of revenue) | B23: =B49/B27 -> 0.4791116 | C23: =C49/C27 -> 0.60448573 | D23: =D49/D27 -> 0.36860575 | E23: =E49/E27 -> 0.35459258 | F23: =F49/F27 -> 0.35455633 | G23: 0.355 | H23: 0.355 | I23: 0.355 | J23: 0.355 | K23: 0.355
A24: Accrued & other current liabilities (% of revenue) | B24: =B57/B27 -> 0.21984424 | C24: =C57/C27 -> 0.20406333 | D24: =D57/D27 -> 0.19361722 | E24: =E57/E27 -> 0.17588301 | F24: =F57/F27 -> 0.16834398 | G24: 0.168 | H24: 0.168 | I24: 0.168 | J24: 0.168 | K24: 0.168
A26: INCOME STATEMENT
A27: Net sales | B27: =Inputs!B15 -> 5803.7 | C27: =Inputs!C15 -> 6401.64 | D27: =Inputs!D15 -> 7409 | E27: =Inputs!E15 -> 7613.47 | F27: =Inputs!F15 -> 7648.15 | G27: =F27*(1+G7) -> 8260.002 | H27: =G27*(1+H7) -> 8920.8022 | I27: =H27*(1+I7) -> 9545.2583 | J27: =I27*(1+J7) -> 10213.426 | K27: =J27*(1+K7) -> 10826.232
A28: Operating expenditure | B28: =Inputs!B16 -> 3006.2 | C28: =Inputs!C16 -> 3172.61 | D28: =Inputs!D16 -> 4077.21 | E28: =Inputs!E16 -> 4007.62 | F28: =Inputs!F16 -> 3666.33 | G28: =G27-G29 -> 3964.801 | H28: =H27-H29 -> 4281.985 | I28: =I27-I29 -> 4581.724 | J28: =J27-J29 -> 4902.4447 | K28: =K27-K29 -> 5196.5913
A29: EBITDA | B29: =B27-B28 -> 2797.5 | C29: =C27-C28 -> 3229.03 | D29: =D27-D28 -> 3331.79 | E29: =E27-E28 -> 3605.85 | F29: =F27-F28 -> 3981.82 | G29: =G27*G8 -> 4295.201 | H29: =H27*H8 -> 4638.8171 | I29: =I27*I8 -> 4963.5343 | J29: =J27*J8 -> 5310.9817 | K29: =K27*K8 -> 5629.6406
A30: Other income | B30: =Inputs!B18 -> 551.75 | C30: =Inputs!C18 -> 301.67 | D30: =Inputs!D18 -> 792.76 | E30: =Inputs!E18 -> 418.08 | F30: =Inputs!F18 -> 205.83 | G30: =G27*G9 -> 223.02005 | H30: =H27*H9 -> 240.86166 | I30: =I27*I9 -> 257.72197 | J30: =J27*J9 -> 275.76251 | K30: =K27*K9 -> 292.30826
A31: Finance cost | B31: =Inputs!B19 -> 1890.62 | C31: =Inputs!C19 -> 1514.63 | D31: =Inputs!D19 -> 1863.32 | E31: =Inputs!E19 -> 1791.94 | F31: =Inputs!F19 -> 1755.15 | G31: =G11*AVERAGE(F43,G43) -> 1670.7624 | H31: =H11*AVERAGE(G43,H43) -> 1569.9085 | I31: =I11*AVERAGE(H43,I43) -> 1475.7661 | J31: =J11*AVERAGE(I43,J43) -> 1390.0966 | K31: =K11*AVERAGE(J43,K43) -> 1312.1373 | L31: Average-balance basis; no circularity because new borrowing is an input
A32: Exceptional items | B32: =Inputs!B20 -> 0 | C32: =Inputs!C20 -> 0 | D32: =Inputs!D20 -> 0 | E32: =Inputs!E20 -> 5804.13 | F32: =Inputs!F20 -> -42.65 | G32: 0 | H32: 0 | I32: 0 | J32: 0 | K32: 0 | L32: Assumed nil in projections
A33: Depreciation & amortisation | B33: =Inputs!B21 -> 682.77 | C33: =Inputs!C21 -> 832.12 | D33: =Inputs!D21 -> 994.95 | E33: =Inputs!E21 -> 1037.63 | F33: =Inputs!F21 -> 1142.04 | G33: =G10*(F51+F52) -> 1099.3954 | H33: =H10*(G51+G52) -> 1084.7032 | I33: =I10*(H51+H52) -> 1070.6869 | J33: =J10*(I51+I52) -> 1057.3153 | K33: =K10*(J51+J52) -> 1044.5588
A34: Profit before tax | B34: =B29+B30-B31+B32-B33 -> 775.86 | C34: =C29+C30-C31+C32-C33 -> 1183.95 | D34: =D29+D30-D31+D32-D33 -> 1266.28 | E34: =E29+E30-E31+E32-E33 -> 6998.49 | F34: =F29+F30-F31+F32-F33 -> 1247.81 | G34: =G29+G30-G31+G32-G33 -> 1748.0633 | H34: =H29+H30-H31+H32-H33 -> 2225.0671 | I34: =I29+I30-I31+I32-I33 -> 2674.8033 | ... K34: =K29+K30-K31+K32-K33 -> 3565.2528
A35: Tax | B35: =Inputs!B23 -> 188.23 | C35: =Inputs!C23 -> 356.94 | D35: =Inputs!D23 -> 345.62 | E35: =Inputs!E23 -> 380.71 | F35: =Inputs!F23 -> 397.46 | G35: =MAX(G34,0)*G12 -> 524.41898 | H35: =MAX(H34,0)*H12 -> 667.52012 | I35: =MAX(I34,0)*I12 -> 802.44099 | J35: =MAX(J34,0)*J12 -> 941.79971 | K35: =MAX(K34,0)*K12 -> 1069.5758
A36: Profit after tax | B36: =B34-B35 -> 587.63 | C36: =C34-C35 -> 827.01 | D36: =D34-D35 -> 920.66 | E36: =E34-E35 -> 6617.78 | F36: =F34-F35 -> 850.35 | G36: =G34-G35 -> 1223.6443 | H36: =H34-H35 -> 1557.547 | I36: =I34-I35 -> 1872.3623 | ... K36: =K34-K35 -> 2495.677
A38: DEBT SCHEDULE (long-term debt incl. current portion)
A39: Opening long-term debt | G39: =F59+F61 -> 19490.96 | H39: =G59+G61 -> 18291.78 | I39: =H59+H61 -> 17145.52 | J39: =I59+I61 -> 16102.423 | K39: =J59+J61 -> 15153.205
A40: Less: scheduled repayment (prior-year current portion) | G40: =F59 -> 1699.18 | H40: =G59 -> 1646.2602 | I40: =H59 -> 1543.0968 | J40: =I59 -> 1449.2181 | K40: =J59 -> 1363.7884
A41: Add: new borrowing | G41: =G16 -> 500 | H41: =H16 -> 500 | I41: =I16 -> 500 | J41: =J16 -> 500 | K41: =K16 -> 500
A42: Closing long-term debt | G42: =G39-G40+G41 -> 18291.78 | H42: =H39-H40+H41 -> 17145.52 | I42: =I39-I40+I41 -> 16102.423 | J42: =J39-J40+J41 -> 15153.205 | K42: =K39-K40+K41 -> 14289.417
A43: Total debt (incl. short-term) | B43: =B58+B59+B61 -> 16703 | C43: =C58+C59+C61 -> 16748.21 | D43: =D58+D59+D61 -> 18653.39 | E43: =E58+E59+E61 -> 20599.3 | F43: =F58+F59+F61 -> 20027.06 | G43: =G58+G59+G61 -> 18827.88 | H43: =H58+H59+H61 -> 17681.62 | I43: =I58+I59+I61 -> 16638.523 | ... K43: =K58+K59+K61 -> 14825.517
A45: BALANCE SHEET
A46: Cash & short-term investments | B46: =Inputs!B29+Inputs!B30 -> 516.48 | C46: =Inputs!C29+Inputs!C30 -> 496.3 | D46: =Inputs!D29+Inputs!D30 -> 497.7 | E46: =Inputs!E29+Inputs!E30 -> 1876.22 | F46: =Inputs!F29+Inputs!F30 -> 527.5 | G46: =F46+G84 -> 480.5345 | H46: =G46+H84 -> 737.51974 | I46: =H46+I84 -> 1363.6406 | J46: =I46+J84 -> 2331.755 | K46: =J46+K84 -> 3644.8471
A47: Trade receivables | B47: =Inputs!B31 -> 1512.9 | C47: =Inputs!C31 -> 2300.1 | D47: =Inputs!D31 -> 1317.6 | E47: =Inputs!E31 -> 994.2 | F47: =Inputs!F31 -> 1075.5 | G47: =G27*G20/Inputs!$B$5 -> 1154.1373 | H47: =H27*H20/Inputs!$B$5 -> 1246.4682 | I47: =I27*I20/Inputs!$B$5 -> 1333.721 | J47: =J27*J20/Inputs!$B$5 -> 1427.0815 | K47: =K27*K20/Inputs!$B$5 -> 1512.7064
A48: Inventory | B48: =Inputs!B33 -> 317.5 | C48: =Inputs!C33 -> 299 | D48: =Inputs!D33 -> 293.1 | E48: =Inputs!E33 -> 338.6 | F48: =Inputs!F33 -> 367 | G48: =G28*G21/Inputs!$B$5 -> 396.4801 | H48: =H28*H21/Inputs!$B$5 -> 428.1985 | I48: =I28*I21/Inputs!$B$5 -> 458.1724 | J48: =J28*J21/Inputs!$B$5 -> 490.24447 | K48: =K28*K21/Inputs!$B$5 -> 519.65913
A49: Other current assets | B49: =Inputs!B32+Inputs!B34+Inputs!B35 -> 2780.62 | C49: =Inputs!C32+Inputs!C34+Inputs!C35 -> 3869.7 | D49: =Inputs!D32+Inputs!D34+Inputs!D35 -> 2731 | E49: =Inputs!E32+Inputs!E34+Inputs!E35 -> 2699.68 | F49: =Inputs!F32+Inputs!F34+Inputs!F35 -> 2711.7 | G49: =G27*G23 -> 2932.3007 | H49: =H27*H23 -> 3166.8848 | I49: =I27*I23 -> 3388.5667 | J49: =J27*J23 -> 3625.7664 | K49: =K27*K23 -> 3843.3124
A50: Total current assets | B50: =B46+B47+B48+B49 -> 5127.5 | C50: =C46+C47+C48+C49 -> 6965.1 | D50: =D46+D47+D48+D49 -> 4839.4 | E50: =E46+E47+E48+E49 -> 5908.7 | F50: =F46+F47+F48+F49 -> 4681.7 | G50: =G46+G47+G48+G49 -> 4963.4526 | H50: =H46+H47+H48+H49 -> 5579.0713 | I50: =I46+I47+I48+I49 -> 6544.1007 | ... K50: =K46+K47+K48+K49 -> 9520.5249
A51: PPE | B51: =Inputs!B37 -> 984.2 | C51: =Inputs!C37 -> 950 | D51: =Inputs!D37 -> 922 | E51: =Inputs!E37 -> 986.3 | F51: =Inputs!F37 -> 946.1 | G51: =F51 -> 946.1 | H51: =G51 -> 946.1 | I51: =H51 -> 946.1 | J51: =I51 -> 946.1 | K51: =J51 -> 946.1
A52: Intangibles (concession rights) | B52: =Inputs!B38 -> 26349.4 | C52: =Inputs!C38 -> 25537.6 | D52: =Inputs!D38 -> 24599.4 | E52: =Inputs!E38 -> 23630.4 | F52: =Inputs!F38 -> 22953.8 | G52: =F52+G14-(G33-G13) -> 22634.405 | H52: =G52+H14-(H33-H13) -> 22329.701 | I52: =H52+I14-(I33-I13) -> 22039.015 | J52: =I52+J14-(J33-J13) -> 21761.699 | K52: =J52+K14-(K33-K13) -> 21497.14
A53: Long-term investments | B53: =Inputs!B39 -> 4440.7 | C53: =Inputs!C39 -> 4945.2 | D53: =Inputs!D39 -> 9377 | E53: =Inputs!E39 -> 17080.6 | F53: =Inputs!F39 -> 19147 | G53: =F53+G15 -> 19147 | H53: =G53+H15 -> 19147 | I53: =H53+I15 -> 19147 | J53: =I53+J15 -> 19147 | K53: =J53+K15 -> 19147
A54: Other non-current assets | B54: =Inputs!B40 -> 5664.8 | C54: =Inputs!C40 -> 4368.3 | D54: =Inputs!D40 -> 5182.5 | E54: =Inputs!E40 -> 6290 | F54: =Inputs!F40 -> 6325 | G54: =F54 -> 6325 | H54: =G54 -> 6325 | I54: =H54 -> 6325 | J54: =I54 -> 6325 | K54: =J54 -> 6325
A55: Total assets | B55: =B50+B51+B52+B53+B54 -> 42566.6 | C55: =C50+C51+C52+C53+C54 -> 42766.2 | D55: =D50+D51+D52+D53+D54 -> 44920.3 | E55: =E50+E51+E52+E53+E54 -> 53896 | F55: =F50+F51+F52+F53+F54 -> 54053.6 | G55: =G50+G51+G52+G53+G54 -> 54015.957 | H55: =H50+H51+H52+H53+H54 -> 54326.873 | I55: =I50+I51+I52+I53+I54 -> 55001.215 | ... K55: =K50+K51+K52+K53+K54 -> 57435.765
A56: Trade payables | B56: =Inputs!B44 -> 381.7 | C56: =Inputs!C44 -> 502.2 | D56: =Inputs!D44 -> 675.7 | E56: =Inputs!E44 -> 521.8 | F56: =Inputs!F44 -> 256.8 | G56: =G28*G22/Inputs!$B$5 -> 278.07919 | H56: =H28*H22/Inputs!$B$5 -> 300.32553 | I56: =I28*I22/Inputs!$B$5 -> 321.34831 | J56: =J28*J22/Inputs!$B$5 -> 343.84269 | K56: =K28*K22/Inputs!$B$5 -> 364.47326
A57: Accrued & other current liabilities | B57: =Inputs!B45+Inputs!B48 -> 1275.91 | C57: =Inputs!C45+Inputs!C48 -> 1306.34 | D57: =Inputs!D45+Inputs!D48 -> 1434.51 | E57: =Inputs!E45+Inputs!E48 -> 1339.08 | F57: =Inputs!F45+Inputs!F48 -> 1287.52 | G57: =G27*G24 -> 1387.6803 | H57: =H27*H24 -> 1498.6948 | I57: =I27*I24 -> 1603.6034 | J57: =J27*J24 -> 1715.8556 | K57: =K27*K24 -> 1818.807
A58: Short-term borrowings | B58: =Inputs!B46 -> 583.3 | C58: =Inputs!C46 -> 1339.1 | D58: =Inputs!D46 -> 589.1 | E58: =Inputs!E46 -> 431.9 | F58: =Inputs!F46 -> 536.1 | G58: =F58+G17 -> 536.1 | H58: =G58+H17 -> 536.1 | I58: =H58+I17 -> 536.1 | J58: =I58+J17 -> 536.1 | K58: =J58+K17 -> 536.1
A59: Current portion of long-term debt | B59: =Inputs!B47 -> 636.49 | C59: =Inputs!C47 -> 1156.86 | D59: =Inputs!D47 -> 1209.99 | E59: =Inputs!E47 -> 1453.42 | F59: =Inputs!F47 -> 1699.18 | G59: =G42*G18 -> 1646.2602 | H59: =H42*H18 -> 1543.0968 | I59: =I42*I18 -> 1449.2181 | J59: =J42*J18 -> 1363.7884 | K59: =K42*K18 -> 1286.0475
A60: Total current liabilities | B60: =B56+B57+B58+B59 -> 2877.4 | C60: =C56+C57+C58+C59 -> 4304.5 | D60: =D56+D57+D58+D59 -> 3909.3 | E60: =E56+E57+E58+E59 -> 3746.2 | F60: =F56+F57+F58+F59 -> 3779.6 | G60: =G56+G57+G58+G59 -> 3848.1197 | H60: =H56+H57+H58+H59 -> 3878.2171 | I60: =I56+I57+I58+I59 -> 3910.2698 | ... K60: =K56+K57+K58+K59 -> 4005.4277
A61: Long-term debt | B61: =Inputs!B50 -> 15483.21 | C61: =Inputs!C50 -> 14252.25 | D61: =Inputs!D50 -> 16854.3 | E61: =Inputs!E50 -> 18713.98 | F61: =Inputs!F50 -> 17791.78 | G61: =G42-G59 -> 16645.52 | H61: =H42-H59 -> 15602.423 | I61: =I42-I59 -> 14653.205 | J61: =J42-J59 -> 13789.417 | K61: =K42-K59 -> 13003.369
A62: Other non-current liabilities | B62: =Inputs!B51 -> 11640.39 | C62: =Inputs!C51 -> 10830.55 | D62: =Inputs!D51 -> 10412.2 | E62: =Inputs!E51 -> 11609.22 | F62: =Inputs!F51 -> 11533.42 | G62: =F62 -> 11533.42 | H62: =G62 -> 11533.42 | I62: =H62 -> 11533.42 | J62: =I62 -> 11533.42 | K62: =J62 -> 11533.42
A63: Total outside liabilities | B63: =B60+B61+B62 -> 30001 | C63: =C60+C61+C62 -> 29387.3 | D63: =D60+D61+D62 -> 31175.8 | E63: =E60+E61+E62 -> 34069.4 | F63: =F60+F61+F62 -> 33104.8 | G63: =G60+G61+G62 -> 32027.06 | H63: =H60+H61+H62 -> 31014.06 | I63: =I60+I61+I62 -> 30096.895 | ... K63: =K60+K61+K62 -> 28542.217
A64: Total equity (net worth) | B64: =Inputs!B55 -> 12565.6 | C64: =Inputs!C55 -> 13378.9 | D64: =Inputs!D55 -> 13744.5 | E64: =Inputs!E55 -> 19826.6 | F64: =Inputs!F55 -> 20948.8 | G64: =F64+G36+G83 -> 21988.898 | H64: =G64+H36+H83 -> 23312.813 | I64: =H64+I36+I83 -> 24904.321 | J64: =I64+J36+J83 -> 26772.223 | K64: =J64+K36+K83 -> 28893.549
A65: Total liabilities & equity | B65: =B63+B64 -> 42566.6 | C65: =C63+C64 -> 42766.2 | D65: =D63+D64 -> 44920.3 | E65: =E63+E64 -> 53896 | F65: =F63+F64 -> 54053.6 | G65: =G63+G64 -> 54015.957 | H65: =H63+H64 -> 54326.873 | I65: =I63+I64 -> 55001.215 | ... K65: =K63+K64 -> 57435.765
A66: Check: assets – liabilities & equity | B66: =B55-B65 -> 0 | C66: =C55-C65 -> 0 | D66: =D55-D65 -> 0 | E66: =E55-E65 -> 0 | F66: =F55-F65 -> 0 | G66: =G55-G65 -> 0 | H66: =H55-H65 -> 0 | I66: =I55-I65 -> 0 | ... K66: =K55-K65 -> 0
A68: CASH FLOW (projected years)
A69: Profit after tax | G69: =G36 -> 1223.6443 | H69: =H36 -> 1557.547 | I69: =I36 -> 1872.3623 | J69: =J36 -> 2197.5327 | K69: =K36 -> 2495.677
A70: Add: depreciation & amortisation | G70: =G33 -> 1099.3954 | H70: =H33 -> 1084.7032 | I70: =I33 -> 1070.6869 | J70: =J33 -> 1057.3153 | K70: =K33 -> 1044.5588
A71: (Increase) / decrease in trade receivables | G71: =-(G47-F47) -> -78.637266 | H71: =-(H47-G47) -> -92.330981 | I71: =-(I47-H47) -> -87.252777 | J71: =-(J47-I47) -> -93.360472 | K71: =-(K47-J47) -> -85.62489
A72: (Increase) / decrease in inventory | G72: =-(G48-F48) -> -29.480096 | H72: =-(H48-G48) -> -31.718408 | I72: =-(I48-H48) -> -29.973895 | J72: =-(J48-I48) -> -32.072068 | K72: =-(K48-J48) -> -29.414668
A73: (Increase) / decrease in other current assets | G73: =-(G49-F49) -> -220.60071 | H73: =-(H49-G49) -> -234.58406 | I73: =-(I49-H49) -> -221.68193 | J73: =-(J49-I49) -> -237.19967 | K73: =-(K49-J49) -> -217.54598
A74: Increase / (decrease) in trade payables | G74: =G56-F56 -> 21.279191 | H74: =H56-G56 -> 22.246335 | I74: =I56-H56 -> 21.022787 | J74: =J56-I56 -> 22.494382 | K74: =K56-J56 -> 20.630562
A75: Increase / (decrease) in accrued & other CL | G75: =G57-F57 -> 100.16034 | H75: =H57-G57 -> 111.01443 | I75: =I57-H57 -> 104.90863 | J75: =J57-I57 -> 112.25224 | K75: =K57-J57 -> 102.95134
A76: Cash flow from operations (after interest) | B76: =Inputs!B64 -> 364.1 | C76: =Inputs!C64 -> 1764.1 | D76: =Inputs!D64 -> 4053.8 | E76: =Inputs!E64 -> 1971.2 | F76: =Inputs!F64 -> 2098 | G76: =SUM(G69:G75) -> 2115.7611 | H76: =SUM(H69:H75) -> 2416.8775 | I76: =SUM(I69:I75) -> 2730.072 | J76: =SUM(J69:J75) -> 3026.9623 | K76: =SUM(K69:K75) -> 3331.2321 | L76: Actual columns: reported CFO (interest shown in financing, so not like-for-like)
A77: Capex — PPE | G77: =-G13 -> -80 | H77: =-H13 -> -80 | I77: =-I13 -> -80 | J77: =-J13 -> -80 | K77: =-K13 -> -80
A78: Capex — concession assets | G78: =-G14 -> -700 | H78: =-H14 -> -700 | I78: =-I14 -> -700 | J78: =-J14 -> -700 | K78: =-K14 -> -700
A79: Net investment in long-term investments | G79: =-G15 -> 0 | H79: =-H15 -> 0 | I79: =-I15 -> 0 | J79: =-J15 -> 0 | K79: =-K15 -> 0
A80: New long-term borrowing | G80: =G41 -> 500 | H80: =H41 -> 500 | I80: =I41 -> 500 | J80: =J41 -> 500 | K80: =K41 -> 500
A81: Scheduled repayment | G81: =-G40 -> -1699.18 | H81: =-H40 -> -1646.2602 | I81: =-I40 -> -1543.0968 | J81: =-J40 -> -1449.2181 | K81: =-K40 -> -1363.7884
A82: Change in short-term borrowings | G82: =G17 -> 0 | H82: =H17 -> 0 | I82: =I17 -> 0 | J82: =J17 -> 0 | K82: =K17 -> 0
A83: Dividends paid | G83: =-MAX(G36,0)*G19 -> -183.54664 | H83: =-MAX(H36,0)*H19 -> -233.63204 | I83: =-MAX(I36,0)*I19 -> -280.85435 | J83: =-MAX(J36,0)*J19 -> -329.6299 | K83: =-MAX(K36,0)*K19 -> -374.35154
A84: Net change in cash | B84: =Inputs!B70 -> -600.8 | C84: =Inputs!C70 -> 253.3 | D84: =Inputs!D70 -> -67.89 | E84: =Inputs!E70 -> 1626.9 | F84: =Inputs!F70 -> -1513.2 | G84: =G76+SUM(G77:G83) -> -46.965497 | H84: =H76+SUM(H77:H83) -> 256.98524 | I84: =I76+SUM(I77:I83) -> 626.12085 | J84: =J76+SUM(J77:J83) -> 968.11437 | K84: =K76+SUM(K77:K83) -> 1313.0921
A86: CREDIT RATIOS
A87: DSCR (x) | B87: n.a. | C87: =IF((C31+B59)>0,(C36-C32+C33+C31)/(C31+B59),"n.a.") -> 1.4753989 | D87: =IF((D31+C59)>0,(D36-D32+D33+D31)/(D31+C59),"n.a.") -> 1.2512267 | E87: =IF((E31+D59)>0,(E36-E32+E33+E31)/(E31+D59),"n.a.") -> 1.2136259 | F87: =IF((F31+E59)>0,(F36-F32+F33+F31)/(F31+E59),"n.a.") -> 1.1812708 | G87: =IF((G31+F59)>0,(G36-G32+G33+G31)/(G31+F59),"n.a.") -> 1.1851247 | H87: =IF((H31+G59)>0,(H36-H32+H33+H31)/(H31+G59),"n.a.") -> 1.3096821 | I87: =IF((I31+H59)>0,(I36-I32+I33+I31)/(I31+H59),"n.a.") -> 1.463735 | J87: =IF((J31+I59)>0,(J36-J32+J33+J31)/(J31+I59),"n.a.") -> 1.6359386 | K87: =IF((K31+J59)>0,(K36-K32+K33+K31)/(K31+J59),"n.a.") -> 1.8133437 | L87: (PAT – exceptional + depreciation + interest) ÷ (interest + prior-year current portion of LT debt)
A88: Tangible net worth | B88: =B64-Inputs!$B$6*B52 -> 12565.6 | C88: =C64-Inputs!$B$6*C52 -> 13378.9 | D88: =D64-Inputs!$B$6*D52 -> 13744.5 | E88: =E64-Inputs!$B$6*E52 -> 19826.6 | F88: =F64-Inputs!$B$6*F52 -> 20948.8 | G88: =G64-Inputs!$B$6*G52 -> 21988.898 | H88: =H64-Inputs!$B$6*H52 -> 23312.813 | I88: =I64-Inputs!$B$6*I52 -> 24904.321 | ... K88: =K64-Inputs!$B$6*K52 -> 28893.549
A89: TOL / TNW (x) | B89: =IF(B88>0,B63/B88,"n.m.") -> 2.3875501 | C89: =IF(C88>0,C63/C88,"n.m.") -> 2.1965408 | D89: =IF(D88>0,D63/D88,"n.m.") -> 2.2682382 | E89: =IF(E88>0,E63/E88,"n.m.") -> 1.7183683 | F89: =IF(F88>0,F63/F88,"n.m.") -> 1.5802719 | G89: =IF(G88>0,G63/G88,"n.m.") -> 1.4565105 | H89: =IF(H88>0,H63/H88,"n.m.") -> 1.330344 | I89: =IF(I88>0,I63/I88,"n.m.") -> 1.2085009 | ... K89: =IF(K88>0,K63/K88,"n.m.") -> 0.98784047
A90: Current ratio (x) | B90: =B50/B60 -> 1.7819907 | C90: =C50/C60 -> 1.6180973 | D90: =D50/D60 -> 1.2379198 | E90: =E50/E60 -> 1.5772516 | F90: =F50/F60 -> 1.2386761 | G90: =G50/G60 -> 1.2898384 | H90: =H50/H60 -> 1.438566 | I90: =I50/I60 -> 1.6735676 | ... K90: =K50/K60 -> 2.3769059
A91: ICR (x) | B91: =(B34-B32+B31)/B31 -> 1.4103733 | C91: =(C34-C32+C31)/C31 -> 1.7816761 | D91: =(D34-D32+D31)/D31 -> 1.6795827 | E91: =(E34-E32+E31)/E31 -> 1.6665179 | F91: =(F34-F32+F31)/F31 -> 1.735242 | G91: =(G34-G32+G31)/G31 -> 2.0462668 | H91: =(H34-H32+H31)/H31 -> 2.4173228 | I91: =(I34-I32+I31)/I31 -> 2.8124845 | ... K91: =(K34-K32+K31)/K31 -> 3.7171339
A92: Debtor days | B92: =B47/B27*Inputs!$B$5 -> 95.147664 | C92: =C47/C27*Inputs!$B$5 -> 131.14397 | D92: =D47/D27*Inputs!$B$5 -> 64.910784 | E92: =E47/E27*Inputs!$B$5 -> 47.663286 | F92: =F47/F27*Inputs!$B$5 -> 51.327118 | G92: =G47/G27*Inputs!$B$5 -> 51 | H92: =H47/H27*Inputs!$B$5 -> 51 | I92: =I47/I27*Inputs!$B$5 -> 51 | ... K92: =K47/K27*Inputs!$B$5 -> 51
A93: Inventory days | B93: =B48/B28*Inputs!$B$5 -> 38.549498 | C93: =C48/C28*Inputs!$B$5 -> 34.399122 | D93: =D48/D28*Inputs!$B$5 -> 26.238899 | E93: =E48/E28*Inputs!$B$5 -> 30.838503 | F93: =F48/F28*Inputs!$B$5 -> 36.536537 | G93: =G48/G28*Inputs!$B$5 -> 36.5 | H93: =H48/H28*Inputs!$B$5 -> 36.5 | I93: =I48/I28*Inputs!$B$5 -> 36.5 | ... K93: =K48/K28*Inputs!$B$5 -> 36.5
A94: Creditor days | B94: =B56/B28*Inputs!$B$5 -> 46.344388 | C94: =C56/C28*Inputs!$B$5 -> 57.77672 | D94: =D56/D28*Inputs!$B$5 -> 60.490016 | E94: =E56/E28*Inputs!$B$5 -> 47.523717 | F94: =F56/F28*Inputs!$B$5 -> 25.56562 | G94: =G56/G28*Inputs!$B$5 -> 25.6 | H94: =H56/H28*Inputs!$B$5 -> 25.6 | I94: =I56/I28*Inputs!$B$5 -> 25.6 | ... K94: =K56/K28*Inputs!$B$5 -> 25.6
A95: Working capital cycle (days) | B95: =B92+B93-B94 -> 87.352774 | C95: =C92+C93-C94 -> 107.76637 | D95: =D92+D93-D94 -> 30.659666 | E95: =E92+E93-E94 -> 30.978072 | F95: =F92+F93-F94 -> 62.298035 | G95: =G92+G93-G94 -> 61.9 | H95: =H92+H93-H94 -> 61.9 | I95: =I92+I93-I94 -> 61.9 | ... K95: =K92+K93-K94 -> 61.9
A96: Total debt / EBITDA (x) | B96: =B43/B29 -> 5.9706881 | C96: =C43/C29 -> 5.186762 | D96: =D43/D29 -> 5.5986092 | E96: =E43/E29 -> 5.7127446 | F96: =F43/F29 -> 5.0296246 | G96: =G43/G29 -> 4.3834689 | H96: =H43/H29 -> 3.8116656 | I96: =I43/I29 -> 3.3521523 | ... K96: =K43/K29 -> 2.6334748
A98: BENCHMARK & INTEGRITY CHECKS
A99: DSCR vs benchmark | C99: =IF(ISNUMBER(C87),IF(C87>=Inputs!$B$7,"OK","BREACH"),"n.a.") -> OK | D99: =IF(ISNUMBER(D87),IF(D87>=Inputs!$B$7,"OK","BREACH"),"n.a.") -> OK | E99: =IF(ISNUMBER(E87),IF(E87>=Inputs!$B$7,"OK","BREACH"),"n.a.") -> OK | F99: =IF(ISNUMBER(F87),IF(F87>=Inputs!$B$7,"OK","BREACH"),"n.a.") -> BREACH | G99: =IF(ISNUMBER(G87),IF(G87>=Inputs!$B$7,"OK","BREACH"),"n.a.") -> BREACH | H99: =IF(ISNUMBER(H87),IF(H87>=Inputs!$B$7,"OK","BREACH"),"n.a.") -> OK | I99: =IF(ISNUMBER(I87),IF(I87>=Inputs!$B$7,"OK","BREACH"),"n.a.") -> OK | J99: =IF(ISNUMBER(J87),IF(J87>=Inputs!$B$7,"OK","BREACH"),"n.a.") -> OK | K99: =IF(ISNUMBER(K87),IF(K87>=Inputs!$B$7,"OK","BREACH"),"n.a.") -> OK
A100: Current ratio vs benchmark | B100: =IF(ISNUMBER(B90),IF(B90>=Inputs!$B$8,"OK","BREACH"),"n.a.") -> OK | C100: =IF(ISNUMBER(C90),IF(C90>=Inputs!$B$8,"OK","BREACH"),"n.a.") -> OK | D100: =IF(ISNUMBER(D90),IF(D90>=Inputs!$B$8,"OK","BREACH"),"n.a.") -> OK | E100: =IF(ISNUMBER(E90),IF(E90>=Inputs!$B$8,"OK","BREACH"),"n.a.") -> OK | F100: =IF(ISNUMBER(F90),IF(F90>=Inputs!$B$8,"OK","BREACH"),"n.a.") -> OK | G100: =IF(ISNUMBER(G90),IF(G90>=Inputs!$B$8,"OK","BREACH"),"n.a.") -> OK | H100: =IF(ISNUMBER(H90),IF(H90>=Inputs!$B$8,"OK","BREACH"),"n.a.") -> OK | I100: =IF(ISNUMBER(I90),IF(I90>=Inputs!$B$8,"OK","BREACH"),"n.a.") -> OK | ... K100: =IF(ISNUMBER(K90),IF(K90>=Inputs!$B$8,"OK","BREACH"),"n.a.") -> OK
A101: TOL/TNW vs benchmark | B101: =IF(ISNUMBER(B89),IF(B89<=Inputs!$B$9,"OK","BREACH"),"n.a.") -> OK | C101: =IF(ISNUMBER(C89),IF(C89<=Inputs!$B$9,"OK","BREACH"),"n.a.") -> OK | D101: =IF(ISNUMBER(D89),IF(D89<=Inputs!$B$9,"OK","BREACH"),"n.a.") -> OK | E101: =IF(ISNUMBER(E89),IF(E89<=Inputs!$B$9,"OK","BREACH"),"n.a.") -> OK | F101: =IF(ISNUMBER(F89),IF(F89<=Inputs!$B$9,"OK","BREACH"),"n.a.") -> OK | G101: =IF(ISNUMBER(G89),IF(G89<=Inputs!$B$9,"OK","BREACH"),"n.a.") -> OK | H101: =IF(ISNUMBER(H89),IF(H89<=Inputs!$B$9,"OK","BREACH"),"n.a.") -> OK | I101: =IF(ISNUMBER(I89),IF(I89<=Inputs!$B$9,"OK","BREACH"),"n.a.") -> OK | ... K101: =IF(ISNUMBER(K89),IF(K89<=Inputs!$B$9,"OK","BREACH"),"n.a.") -> OK
A102: ICR vs benchmark | B102: =IF(ISNUMBER(B91),IF(B91>=Inputs!$B$10,"OK","BREACH"),"n.a.") -> BREACH | C102: =IF(ISNUMBER(C91),IF(C91>=Inputs!$B$10,"OK","BREACH"),"n.a.") -> OK | D102: =IF(ISNUMBER(D91),IF(D91>=Inputs!$B$10,"OK","BREACH"),"n.a.") -> OK | E102: =IF(ISNUMBER(E91),IF(E91>=Inputs!$B$10,"OK","BREACH"),"n.a.") -> OK | F102: =IF(ISNUMBER(F91),IF(F91>=Inputs!$B$10,"OK","BREACH"),"n.a.") -> OK | G102: =IF(ISNUMBER(G91),IF(G91>=Inputs!$B$10,"OK","BREACH"),"n.a.") -> OK | H102: =IF(ISNUMBER(H91),IF(H91>=Inputs!$B$10,"OK","BREACH"),"n.a.") -> OK | I102: =IF(ISNUMBER(I91),IF(I91>=Inputs!$B$10,"OK","BREACH"),"n.a.") -> OK | ... K102: =IF(ISNUMBER(K91),IF(K91>=Inputs!$B$10,"OK","BREACH"),"n.a.") -> OK
A103: Cash balance non-negative | B103: =IF(B46>=0,"OK","SHORTFALL") -> OK | C103: =IF(C46>=0,"OK","SHORTFALL") -> OK | D103: =IF(D46>=0,"OK","SHORTFALL") -> OK | E103: =IF(E46>=0,"OK","SHORTFALL") -> OK | F103: =IF(F46>=0,"OK","SHORTFALL") -> OK | G103: =IF(G46>=0,"OK","SHORTFALL") -> OK | H103: =IF(H46>=0,"OK","SHORTFALL") -> OK | I103: =IF(I46>=0,"OK","SHORTFALL") -> OK | ... K103: =IF(K46>=0,"OK","SHORTFALL") -> OK
A104: Balance sheet balances | B104: =IF(ABS(B66)<0.5,"OK","ERROR") -> OK | C104: =IF(ABS(C66)<0.5,"OK","ERROR") -> OK | D104: =IF(ABS(D66)<0.5,"OK","ERROR") -> OK | E104: =IF(ABS(E66)<0.5,"OK","ERROR") -> OK | F104: =IF(ABS(F66)<0.5,"OK","ERROR") -> OK | G104: =IF(ABS(G66)<0.5,"OK","ERROR") -> OK | H104: =IF(ABS(H66)<0.5,"OK","ERROR") -> OK | I104: =IF(ABS(I66)<0.5,"OK","ERROR") -> OK | ... K104: =IF(ABS(K66)<0.5,"OK","ERROR") -> OK

Sheet Sensitivity
A1: IRB Infrastructure Developers Ltd — Sensitivity Analysis (FY2027E)
A2: Live formulas (no data tables): each cell recomputes FY2027E profit, interest and the ratio from the base-case drivers below. Flexes P&L / debt drivers only; working-capital and cash effects are excluded. Blue deltas are editable.
A4: BASE CASE FY2027E (linked to Projections)
A5: Opening revenue (FY2026A) | B5: =Projections!F27 -> 7648.15
A6: Revenue growth | B6: =Projections!G7 -> 0.08
A7: EBITDA margin | B7: =Projections!G8 -> 0.52
A8: Other income (% of revenue) | B8: =Projections!G9 -> 0.027
A9: Depreciation & amortisation | B9: =Projections!G33 -> 1099.3954
A10: Interest rate | B10: =Projections!G11 -> 0.086
A11: Tax rate | B11: =Projections!G12 -> 0.3
A12: Average total debt (base) | B12: =AVERAGE(Projections!F43,Projections!G43) -> 19427.47
A13: Opening current portion of LT debt | B13: =Projections!F59 -> 1699.18
A14: Total outside liabilities (base) | B14: =Projections!G63 -> 32027.06
A15: Total equity (base) | B15: =Projections!G64 -> 21988.898
A16: Dividend payout | B16: =Projections!G19 -> 0.15
A17: Intangibles (base) | B17: =Projections!G52 -> 22634.405
A18: PAT (base) | B18: =Projections!G36 -> 1223.6443
A19: DSCR per Projections (x) | B19: =Projections!G87 -> 1.1851247
A20: ICR per Projections (x) | B20: =Projections!G91 -> 2.0462668
A21: TOL/TNW per Projections (x) | B21: =Projections!G89 -> 1.4565105
A22: Tie-out: recomputed base DSCR – Projections DSCR (should be 0.00) | B22: =(((($B$5*(1+$B$6))*$B$7+($B$5*(1+$B$6))*$B$8-$B$9-(($B$12+0/2)*($B$10+0)))-MAX((($B$5*(1+$B$6))*$B$7+($B$5*(1+$B$6))*$B$8-$B$9-(($B$12+0/2)*($B$10+0))),0)*$B$11)+$B$9+(($B$12+0/2)*($B$10+0)))/((($B$12+0/2)*($B$10+0))+$B$13)-B19 -> 0
A23: Tie-out: recomputed base TOL/TNW – Projections (should be 0.00) | B23: =IF(($B$15+(((($B$5*(1+$B$6))*$B$7+($B$5*(1+$B$6))*$B$8-$B$9-(($B$12+0/2)*($B$10+0)))-MAX((($B$5*(1+$B$6))*$B$7+($B$5*(1+$B$6))*$B$8-$B$9-(($B$12+0/2)*($B$10+0))),0)*$B$11)-$B$18)*(1-$B$16)-Inputs!$B$6*$B$17)>0,($B$14+0)/($B$15+(((($B$5*(1+$B$6))*$B$7+($B$5*(1+$B$6))*$B$8-$B$9-(($B$12+0/2)*($B$10+0)))-MAX((($B$5*(1+$B$6))*$B$7+($B$5*(1+$B$6))*$B$8-$B$9-(($B$12+0/2)*($B$10+0))),0)*$B$11)-$B$18)*(1-$B$16)-Inputs!$B$6*$B$17),"n.m.")-B21 -> 0
A25: 1. DSCR (x): revenue growth vs interest-rate change
A26: Rows: Revenue growth | Columns: Interest rate | B26: Δ vs base → | C26: -0.01 | D26: -0.005 | E26: 0 | F26: 0.005 | G26: 0.01 | H26: 0.02
B27: Level → | C27: =$B$10+C26 -> 0.076 | D27: =$B$10+D26 -> 0.081 | E27: =$B$10+E26 -> 0.086 | F27: =$B$10+F26 -> 0.091 | G27: =$B$10+G26 -> 0.096 | H27: =$B$10+H26 -> 0.106
A28: -0.15 | B28: =$B$6+A28 -> -0.07 | C28: =(((($B$5*(1+$B28))*$B$7+($B$5*(1+$B28))*$B$8-$B$9-(($B$12+0/2)*($B$10+C$26)))-MAX((($B$5*(1+$B28))*$B$7+($B$5*(1+$B28))*$B$8-$B$9-(($B$12+0/2)*($B$10+C$26))),0)*$B$11)+$B$9+(($B$12+0/2)*($B$10+C$26)))/((($B$12+0/2)*($B$10+C$26))+$B$13) -> 1.100949 | D28: =(((($B$5*(1+$B28))*$B$7+($B$5*(1+$B28))*$B$8-$B$9-(($B$12+0/2)*($B$10+D$26)))-MAX((($B$5*(1+$B28))*$B$7+($B$5*(1+$B28))*$B$8-$B$9-(($B$12+0/2)*($B$10+D$26))),0)*$B$11)+$B$9+(($B$12+0/2)*($B$10+D$26)))/((($B$12+0/2)*($B$10+D$26))+$B$13) -> 1.0771767 | E28: =(((($B$5*(1+$B28))*$B$7+($B$5*(1+$B28))*$B$8-$B$9-(($B$12+0/2)*($B$10+E$26)))-MAX((($B$5*(1+$B28))*$B$7+($B$5*(1+$B28))*$B$8-$B$9-(($B$12+0/2)*($B$10+E$26))),0)*$B$11)+$B$9+(($B$12+0/2)*($B$10+E$26)))/((($B$12+0/2)*($B$10+E$26))+$B$13) -> 1.0547749 | F28: =(((($B$5*(1+$B28))*$B$7+($B$5*(1+$B28))*$B$8-$B$9-(($B$12+0/2)*($B$10+F$26)))-MAX((($B$5*(1+$B28))*$B$7+($B$5*(1+$B28))*$B$8-$B$9-(($B$12+0/2)*($B$10+F$26))),0)*$B$11)+$B$9+(($B$12+0/2)*($B$10+F$26)))/((($B$12+0/2)*($B$10+F$26))+$B$13) -> 1.0336283 | G28: =(((($B$5*(1+$B28))*$B$7+($B$5*(1+$B28))*$B$8-$B$9-(($B$12+0/2)*($B$10+G$26)))-MAX((($B$5*(1+$B28))*$B$7+($B$5*(1+$B28))*$B$8-$B$9-(($B$12+0/2)*($B$10+G$26))),0)*$B$11)+$B$9+(($B$12+0/2)*($B$10+G$26)))/((($B$12+0/2)*($B$10+G$26))+$B$13) -> 1.0136344 | H28: =(((($B$5*(1+$B28))*$B$7+($B$5*(1+$B28))*$B$8-$B$9-(($B$12+0/2)*($B$10+H$26)))-MAX((($B$5*(1+$B28))*$B$7+($B$5*(1+$B28))*$B$8-$B$9-(($B$12+0/2)*($B$10+H$26))),0)*$B$11)+$B$9+(($B$12+0/2)*($B$10+H$26)))/((($B$12+0/2)*($B$10+H$26))+$B$13) -> 0.97674695
A29: -0.1 | B29: =$B$6+A29 -> -0.02 | C29: =(((($B$5*(1+$B29))*$B$7+($B$5*(1+$B29))*$B$8-$B$9-(($B$12+0/2)*($B$10+C$26)))-MAX((($B$5*(1+$B29))*$B$7+($B$5*(1+$B29))*$B$8-$B$9-(($B$12+0/2)*($B$10+C$26))),0)*$B$11)+$B$9+(($B$12+0/2)*($B$10+C$26)))/((($B$12+0/2)*($B$10+C$26))+$B$13) -> 1.147057 | D29: =(((($B$5*(1+$B29))*$B$7+($B$5*(1+$B29))*$B$8-$B$9-(($B$12+0/2)*($B$10+D$26)))-MAX((($B$5*(1+$B29))*$B$7+($B$5*(1+$B29))*$B$8-$B$9-(($B$12+0/2)*($B$10+D$26))),0)*$B$11)+$B$9+(($B$12+0/2)*($B$10+D$26)))/((($B$12+0/2)*($B$10+D$26))+$B$13) -> 1.1219163 | E29: =(((($B$5*(1+$B29))*$B$7+($B$5*(1+$B29))*$B$8-$B$9-(($B$12+0/2)*($B$10+E$26)))-MAX((($B$5*(1+$B29))*$B$7+($B$5*(1+$B29))*$B$8-$B$9-(($B$12+0/2)*($B$10+E$26))),0)*$B$11)+$B$9+(($B$12+0/2)*($B$10+E$26)))/((($B$12+0/2)*($B$10+E$26))+$B$13) -> 1.0982248 | F29: =(((($B$5*(1+$B29))*$B$7+($B$5*(1+$B29))*$B$8-$B$9-(($B$12+0/2)*($B$10+F$26)))-MAX((($B$5*(1+$B29))*$B$7+($B$5*(1+$B29))*$B$8-$B$9-(($B$12+0/2)*($B$10+F$26))),0)*$B$11)+$B$9+(($B$12+0/2)*($B$10+F$26)))/((($B$12+0/2)*($B$10+F$26))+$B$13) -> 1.0758609 | G29: =(((($B$5*(1+$B29))*$B$7+($B$5*(1+$B29))*$B$8-$B$9-(($B$12+0/2)*($B$10+G$26)))-MAX((($B$5*(1+$B29))*$B$7+($B$5*(1+$B29))*$B$8-$B$9-(($B$12+0/2)*($B$10+G$26))),0)*$B$11)+$B$9+(($B$12+0/2)*($B$10+G$26)))/((($B$12+0/2)*($B$10+G$26))+$B$13) -> 1.054716 | H29: =(((($B$5*(1+$B29))*$B$7+($B$5*(1+$B29))*$B$8-$B$9-(($B$12+0/2)*($B$10+H$26)))-MAX((($B$5*(1+$B29))*$B$7+($B$5*(1+$B29))*$B$8-$B$9-(($B$12+0/2)*($B$10+H$26))),0)*$B$11)+$B$9+(($B$12+0/2)*($B$10+H$26)))/((($B$12+0/2)*($B$10+H$26))+$B$13) -> 1.0157051
A30: -0.05 | B30: =$B$6+A30 -> 0.03 | C30: =(((($B$5*(1+$B30))*$B$7+($B$5*(1+$B30))*$B$8-$B$9-(($B$12+0/2)*($B$10+C$26)))-MAX((($B$5*(1+$B30))*$B$7+($B$5*(1+$B30))*$B$8-$B$9-(($B$12+0/2)*($B$10+C$26))),0)*$B$11)+$B$9+(($B$12+0/2)*($B$10+C$26)))/((($B$12+0/2)*($B$10+C$26))+$B$13) -> 1.1931651 | D30: =(((($B$5*(1+$B30))*$B$7+($B$5*(1+$B30))*$B$8-$B$9-(($B$12+0/2)*($B$10+D$26)))-MAX((($B$5*(1+$B30))*$B$7+($B$5*(1+$B30))*$B$8-$B$9-(($B$12+0/2)*($B$10+D$26))),0)*$B$11)+$B$9+(($B$12+0/2)*($B$10+D$26)))/((($B$12+0/2)*($B$10+D$26))+$B$13) -> 1.1666558 | E30: =(((($B$5*(1+$B30))*$B$7+($B$5*(1+$B30))*$B$8-$B$9-(($B$12+0/2)*($B$10+E$26)))-MAX((($B$5*(1+$B30))*$B$7+($B$5*(1+$B30))*$B$8-$B$9-(($B$12+0/2)*($B$10+E$26))),0)*$B$11)+$B$9+(($B$12+0/2)*($B$10+E$26)))/((($B$12+0/2)*($B$10+E$26))+$B$13) -> 1.1416748 | F30: =(((($B$5*(1+$B30))*$B$7+($B$5*(1+$B30))*$B$8-$B$9-(($B$12+0/2)*($B$10+F$26)))-MAX((($B$5*(1+$B30))*$B$7+($B$5*(1+$B30))*$B$8-$B$9-(($B$12+0/2)*($B$10+F$26))),0)*$B$11)+$B$9+(($B$12+0/2)*($B$10+F$26)))/((($B$12+0/2)*($B$10+F$26))+$B$13) -> 1.1180935 | G30: =(((($B$5*(1+$B30))*$B$7+($B$5*(1+$B30))*$B$8-$B$9-(($B$12+0/2)*($B$10+G$26)))-MAX((($B$5*(1+$B30))*$B$7+($B$5*(1+$B30))*$B$8-$B$9-(($B$12+0/2)*($B$10+G$26))),0)*$B$11)+$B$9+(($B$12+0/2)*($B$10+G$26)))/((($B$12+0/2)*($B$10+G$26))+$B$13) -> 1.0957976 | H30: =(((($B$5*(1+$B30))*$B$7+($B$5*(1+$B30))*$B$8-$B$9-(($B$12+0/2)*($B$10+H$26)))-MAX((($B$5*(1+$B30))*$B$7+($B$5*(1+$B30))*$B$8-$B$9-(($B$12+0/2)*($B$10+H$26))),0)*$B$11)+$B$9+(($B$12+0/2)*($B$10+H$26)))/((($B$12+0/2)*($B$10+H$26))+$B$13) -> 1.0546632
A31: 0 | B31: =$B$6+A31 -> 0.08 | C31: =(((($B$5*(1+$B31))*$B$7+($B$5*(1+$B31))*$B$8-$B$9-(($B$12+0/2)*($B$10+C$26)))-MAX((($B$5*(1+$B31))*$B$7+($B$5*(1+$B31))*$B$8-$B$9-(($B$12+0/2)*($B$10+C$26))),0)*$B$11)+$B$9+(($B$12+0/2)*($B$10+C$26)))/((($B$12+0/2)*($B$10+C$26))+$B$13) -> 1.2392731 | D31: =(((($B$5*(1+$B31))*$B$7+($B$5*(1+$B31))*$B$8-$B$9-(($B$12+0/2)*($B$10+D$26)))-MAX((($B$5*(1+$B31))*$B$7+($B$5*(1+$B31))*$B$8-$B$9-(($B$12+0/2)*($B$10+D$26))),0)*$B$11)+$B$9+(($B$12+0/2)*($B$10+D$26)))/((($B$12+0/2)*($B$10+D$26))+$B$13) -> 1.2113954 | E31: =(((($B$5*(1+$B31))*$B$7+($B$5*(1+$B31))*$B$8-$B$9-(($B$12+0/2)*($B$10+E$26)))-MAX((($B$5*(1+$B31))*$B$7+($B$5*(1+$B31))*$B$8-$B$9-(($B$12+0/2)*($B$10+E$26))),0)*$B$11)+$B$9+(($B$12+0/2)*($B$10+E$26)))/((($B$12+0/2)*($B$10+E$26))+$B$13) -> 1.1851247 | F31: =(((($B$5*(1+$B31))*$B$7+($B$5*(1+$B31))*$B$8-$B$9-(($B$12+0/2)*($B$10+F$26)))-MAX((($B$5*(1+$B31))*$B$7+($B$5*(1+$B31))*$B$8-$B$9-(($B$12+0/2)*($B$10+F$26))),0)*$B$11)+$B$9+(($B$12+0/2)*($B$10+F$26)))/((($B$12+0/2)*($B$10+F$26))+$B$13) -> 1.1603261 | G31: =(((($B$5*(1+$B31))*$B$7+($B$5*(1+$B31))*$B$8-$B$9-(($B$12+0/2)*($B$10+G$26)))-MAX((($B$5*(1+$B31))*$B$7+($B$5*(1+$B31))*$B$8-$B$9-(($B$12+0/2)*($B$10+G$26))),0)*$B$11)+$B$9+(($B$12+0/2)*($B$10+G$26)))/((($B$12+0/2)*($B$10+G$26))+$B$13) -> 1.1368793 | H31: =(((($B$5*(1+$B31))*$B$7+($B$5*(1+$B31))*$B$8-$B$9-(($B$12+0/2)*($B$10+H$26)))-MAX((($B$5*(1+$B31))*$B$7+($B$5*(1+$B31))*$B$8-$B$9-(($B$12+0/2)*($B$10+H$26))),0)*$B$11)+$B$9+(($B$12+0/2)*($B$10+H$26)))/((($B$12+0/2)*($B$10+H$26))+$B$13) -> 1.0936214
A32: 0.05 | B32: =$B$6+A32 -> 0.13 | C32: =(((($B$5*(1+$B32))*$B$7+($B$5*(1+$B32))*$B$8-$B$9-(($B$12+0/2)*($B$10+C$26)))-MAX((($B$5*(1+$B32))*$B$7+($B$5*(1+$B32))*$B$8-$B$9-(($B$12+0/2)*($B$10+C$26))),0)*$B$11)+$B$9+(($B$12+0/2)*($B$10+C$26)))/((($B$12+0/2)*($B$10+C$26))+$B$13) -> 1.2853812 | D32: =(((($B$5*(1+$B32))*$B$7+($B$5*(1+$B32))*$B$8-$B$9-(($B$12+0/2)*($B$10+D$26)))-MAX((($B$5*(1+$B32))*$B$7+($B$5*(1+$B32))*$B$8-$B$9-(($B$12+0/2)*($B$10+D$26))),0)*$B$11)+$B$9+(($B$12+0/2)*($B$10+D$26)))/((($B$12+0/2)*($B$10+D$26))+$B$13) -> 1.2561349 | E32: =(((($B$5*(1+$B32))*$B$7+($B$5*(1+$B32))*$B$8-$B$9-(($B$12+0/2)*($B$10+E$26)))-MAX((($B$5*(1+$B32))*$B$7+($B$5*(1+$B32))*$B$8-$B$9-(($B$12+0/2)*($B$10+E$26))),0)*$B$11)+$B$9+(($B$12+0/2)*($B$10+E$26)))/((($B$12+0/2)*($B$10+E$26))+$B$13) -> 1.2285747 | F32: =(((($B$5*(1+$B32))*$B$7+($B$5*(1+$B32))*$B$8-$B$9-(($B$12+0/2)*($B$10+F$26)))-MAX((($B$5*(1+$B32))*$B$7+($B$5*(1+$B32))*$B$8-$B$9-(($B$12+0/2)*($B$10+F$26))),0)*$B$11)+$B$9+(($B$12+0/2)*($B$10+F$26)))/((($B$12+0/2)*($B$10+F$26))+$B$13) -> 1.2025588 | G32: =(((($B$5*(1+$B32))*$B$7+($B$5*(1+$B32))*$B$8-$B$9-(($B$12+0/2)*($B$10+G$26)))-MAX((($B$5*(1+$B32))*$B$7+($B$5*(1+$B32))*$B$8-$B$9-(($B$12+0/2)*($B$10+G$26))),0)*$B$11)+$B$9+(($B$12+0/2)*($B$10+G$26)))/((($B$12+0/2)*($B$10+G$26))+$B$13) -> 1.1779609 | H32: =(((($B$5*(1+$B32))*$B$7+($B$5*(1+$B32))*$B$8-$B$9-(($B$12+0/2)*($B$10+H$26)))-MAX((($B$5*(1+$B32))*$B$7+($B$5*(1+$B32))*$B$8-$B$9-(($B$12+0/2)*($B$10+H$26))),0)*$B$11)+$B$9+(($B$12+0/2)*($B$10+H$26)))/((($B$12+0/2)*($B$10+H$26))+$B$13) -> 1.1325795
A33: 0.1 | B33: =$B$6+A33 -> 0.18 | C33: =(((($B$5*(1+$B33))*$B$7+($B$5*(1+$B33))*$B$8-$B$9-(($B$12+0/2)*($B$10+C$26)))-MAX((($B$5*(1+$B33))*$B$7+($B$5*(1+$B33))*$B$8-$B$9-(($B$12+0/2)*($B$10+C$26))),0)*$B$11)+$B$9+(($B$12+0/2)*($B$10+C$26)))/((($B$12+0/2)*($B$10+C$26))+$B$13) -> 1.3314892 | D33: =(((($B$5*(1+$B33))*$B$7+($B$5*(1+$B33))*$B$8-$B$9-(($B$12+0/2)*($B$10+D$26)))-MAX((($B$5*(1+$B33))*$B$7+($B$5*(1+$B33))*$B$8-$B$9-(($B$12+0/2)*($B$10+D$26))),0)*$B$11)+$B$9+(($B$12+0/2)*($B$10+D$26)))/((($B$12+0/2)*($B$10+D$26))+$B$13) -> 1.3008745 | E33: =(((($B$5*(1+$B33))*$B$7+($B$5*(1+$B33))*$B$8-$B$9-(($B$12+0/2)*($B$10+E$26)))-MAX((($B$5*(1+$B33))*$B$7+($B$5*(1+$B33))*$B$8-$B$9-(($B$12+0/2)*($B$10+E$26))),0)*$B$11)+$B$9+(($B$12+0/2)*($B$10+E$26)))/((($B$12+0/2)*($B$10+E$26))+$B$13) -> 1.2720246 | F33: =(((($B$5*(1+$B33))*$B$7+($B$5*(1+$B33))*$B$8-$B$9-(($B$12+0/2)*($B$10+F$26)))-MAX((($B$5*(1+$B33))*$B$7+($B$5*(1+$B33))*$B$8-$B$9-(($B$12+0/2)*($B$10+F$26))),0)*$B$11)+$B$9+(($B$12+0/2)*($B$10+F$26)))/((($B$12+0/2)*($B$10+F$26))+$B$13) -> 1.2447914 | G33: =(((($B$5*(1+$B33))*$B$7+($B$5*(1+$B33))*$B$8-$B$9-(($B$12+0/2)*($B$10+G$26)))-MAX((($B$5*(1+$B33))*$B$7+($B$5*(1+$B33))*$B$8-$B$9-(($B$12+0/2)*($B$10+G$26))),0)*$B$11)+$B$9+(($B$12+0/2)*($B$10+G$26)))/((($B$12+0/2)*($B$10+G$26))+$B$13) -> 1.2190425 | H33: =(((($B$5*(1+$B33))*$B$7+($B$5*(1+$B33))*$B$8-$B$9-(($B$12+0/2)*($B$10+H$26)))-MAX((($B$5*(1+$B33))*$B$7+($B$5*(1+$B33))*$B$8-$B$9-(($B$12+0/2)*($B$10+H$26))),0)*$B$11)+$B$9+(($B$12+0/2)*($B$10+H$26)))/((($B$12+0/2)*($B$10+H$26))+$B$13) -> 1.1715376
A36: 2. DSCR (x): EBITDA margin vs revenue growth
A37: Rows: EBITDA margin | Columns: Revenue growth | B37: Δ vs base → | C37: -0.15 | D37: -0.1 | E37: -0.05 | F37: 0 | G37: 0.05 | H37: 0.1
B38: Level → | C38: =$B$6+C37 -> -0.07 | D38: =$B$6+D37 -> -0.02 | E38: =$B$6+E37 -> 0.03 | F38: =$B$6+F37 -> 0.08 | G38: =$B$6+G37 -> 0.13 | H38: =$B$6+H37 -> 0.18
A39: -0.1 | B39: =$B$7+A39 -> 0.42 | C39: =(((($B$5*(1+C$38))*$B39+($B$5*(1+C$38))*$B$8-$B$9-(($B$12+0/2)*($B$10+0)))-MAX((($B$5*(1+C$38))*$B39+($B$5*(1+C$38))*$B$8-$B$9-(($B$12+0/2)*($B$10+0))),0)*$B$11)+$B$9+(($B$12+0/2)*($B$10+0)))/((($B$12+0/2)*($B$10+0))+$B$13) -> 0.90702916 | D39: =(((($B$5*(1+D$38))*$B39+($B$5*(1+D$38))*$B$8-$B$9-(($B$12+0/2)*($B$10+0)))-MAX((($B$5*(1+D$38))*$B39+($B$5*(1+D$38))*$B$8-$B$9-(($B$12+0/2)*($B$10+0))),0)*$B$11)+$B$9+(($B$12+0/2)*($B$10+0)))/((($B$12+0/2)*($B$10+0))+$B$13) -> 0.9425358 | E39: =(((($B$5*(1+E$38))*$B39+($B$5*(1+E$38))*$B$8-$B$9-(($B$12+0/2)*($B$10+0)))-MAX((($B$5*(1+E$38))*$B39+($B$5*(1+E$38))*$B$8-$B$9-(($B$12+0/2)*($B$10+0))),0)*$B$11)+$B$9+(($B$12+0/2)*($B$10+0)))/((($B$12+0/2)*($B$10+0))+$B$13) -> 0.97804243 | F39: =(((($B$5*(1+F$38))*$B39+($B$5*(1+F$38))*$B$8-$B$9-(($B$12+0/2)*($B$10+0)))-MAX((($B$5*(1+F$38))*$B39+($B$5*(1+F$38))*$B$8-$B$9-(($B$12+0/2)*($B$10+0))),0)*$B$11)+$B$9+(($B$12+0/2)*($B$10+0)))/((($B$12+0/2)*($B$10+0))+$B$13) -> 1.0135491 | G39: =(((($B$5*(1+G$38))*$B39+($B$5*(1+G$38))*$B$8-$B$9-(($B$12+0/2)*($B$10+0)))-MAX((($B$5*(1+G$38))*$B39+($B$5*(1+G$38))*$B$8-$B$9-(($B$12+0/2)*($B$10+0))),0)*$B$11)+$B$9+(($B$12+0/2)*($B$10+0)))/((($B$12+0/2)*($B$10+0))+$B$13) -> 1.0490557 | H39: =(((($B$5*(1+H$38))*$B39+($B$5*(1+H$38))*$B$8-$B$9-(($B$12+0/2)*($B$10+0)))-MAX((($B$5*(1+H$38))*$B39+($B$5*(1+H$38))*$B$8-$B$9-(($B$12+0/2)*($B$10+0))),0)*$B$11)+$B$9+(($B$12+0/2)*($B$10+0)))/((($B$12+0/2)*($B$10+0))+$B$13) -> 1.0845623
A40: -0.05 | B40: =$B$7+A40 -> 0.47 | C40: =(((($B$5*(1+C$38))*$B40+($B$5*(1+C$38))*$B$8-$B$9-(($B$12+0/2)*($B$10+0)))-MAX((($B$5*(1+C$38))*$B40+($B$5*(1+C$38))*$B$8-$B$9-(($B$12+0/2)*($B$10+0))),0)*$B$11)+$B$9+(($B$12+0/2)*($B$10+0)))/((($B$12+0/2)*($B$10+0))+$B$13) -> 0.98090202 | D40: =(((($B$5*(1+D$38))*$B40+($B$5*(1+D$38))*$B$8-$B$9-(($B$12+0/2)*($B$10+0)))-MAX((($B$5*(1+D$38))*$B40+($B$5*(1+D$38))*$B$8-$B$9-(($B$12+0/2)*($B$10+0))),0)*$B$11)+$B$9+(($B$12+0/2)*($B$10+0)))/((($B$12+0/2)*($B$10+0))+$B$13) -> 1.0203803 | E40: =(((($B$5*(1+E$38))*$B40+($B$5*(1+E$38))*$B$8-$B$9-(($B$12+0/2)*($B$10+0)))-MAX((($B$5*(1+E$38))*$B40+($B$5*(1+E$38))*$B$8-$B$9-(($B$12+0/2)*($B$10+0))),0)*$B$11)+$B$9+(($B$12+0/2)*($B$10+0)))/((($B$12+0/2)*($B$10+0))+$B$13) -> 1.0598586 | F40: =(((($B$5*(1+F$38))*$B40+($B$5*(1+F$38))*$B$8-$B$9-(($B$12+0/2)*($B$10+0)))-MAX((($B$5*(1+F$38))*$B40+($B$5*(1+F$38))*$B$8-$B$9-(($B$12+0/2)*($B$10+0))),0)*$B$11)+$B$9+(($B$12+0/2)*($B$10+0)))/((($B$12+0/2)*($B$10+0))+$B$13) -> 1.0993369 | G40: =(((($B$5*(1+G$38))*$B40+($B$5*(1+G$38))*$B$8-$B$9-(($B$12+0/2)*($B$10+0)))-MAX((($B$5*(1+G$38))*$B40+($B$5*(1+G$38))*$B$8-$B$9-(($B$12+0/2)*($B$10+0))),0)*$B$11)+$B$9+(($B$12+0/2)*($B$10+0)))/((($B$12+0/2)*($B$10+0))+$B$13) -> 1.1388152 | H40: =(((($B$5*(1+H$38))*$B40+($B$5*(1+H$38))*$B$8-$B$9-(($B$12+0/2)*($B$10+0)))-MAX((($B$5*(1+H$38))*$B40+($B$5*(1+H$38))*$B$8-$B$9-(($B$12+0/2)*($B$10+0))),0)*$B$11)+$B$9+(($B$12+0/2)*($B$10+0)))/((($B$12+0/2)*($B$10+0))+$B$13) -> 1.1782935
A41: -0.025 | B41: =$B$7+A41 -> 0.495 | C41: =(((($B$5*(1+C$38))*$B41+($B$5*(1+C$38))*$B$8-$B$9-(($B$12+0/2)*($B$10+0)))-MAX((($B$5*(1+C$38))*$B41+($B$5*(1+C$38))*$B$8-$B$9-(($B$12+0/2)*($B$10+0))),0)*$B$11)+$B$9+(($B$12+0/2)*($B$10+0)))/((($B$12+0/2)*($B$10+0))+$B$13) -> 1.0178385 | D41: =(((($B$5*(1+D$38))*$B41+($B$5*(1+D$38))*$B$8-$B$9-(($B$12+0/2)*($B$10+0)))-MAX((($B$5*(1+D$38))*$B41+($B$5*(1+D$38))*$B$8-$B$9-(($B$12+0/2)*($B$10+0))),0)*$B$11)+$B$9+(($B$12+0/2)*($B$10+0)))/((($B$12+0/2)*($B$10+0))+$B$13) -> 1.0593026 | E41: =(((($B$5*(1+E$38))*$B41+($B$5*(1+E$38))*$B$8-$B$9-(($B$12+0/2)*($B$10+0)))-MAX((($B$5*(1+E$38))*$B41+($B$5*(1+E$38))*$B$8-$B$9-(($B$12+0/2)*($B$10+0))),0)*$B$11)+$B$9+(($B$12+0/2)*($B$10+0)))/((($B$12+0/2)*($B$10+0))+$B$13) -> 1.1007667 | F41: =(((($B$5*(1+F$38))*$B41+($B$5*(1+F$38))*$B$8-$B$9-(($B$12+0/2)*($B$10+0)))-MAX((($B$5*(1+F$38))*$B41+($B$5*(1+F$38))*$B$8-$B$9-(($B$12+0/2)*($B$10+0))),0)*$B$11)+$B$9+(($B$12+0/2)*($B$10+0)))/((($B$12+0/2)*($B$10+0))+$B$13) -> 1.1422308 | G41: =(((($B$5*(1+G$38))*$B41+($B$5*(1+G$38))*$B$8-$B$9-(($B$12+0/2)*($B$10+0)))-MAX((($B$5*(1+G$38))*$B41+($B$5*(1+G$38))*$B$8-$B$9-(($B$12+0/2)*($B$10+0))),0)*$B$11)+$B$9+(($B$12+0/2)*($B$10+0)))/((($B$12+0/2)*($B$10+0))+$B$13) -> 1.1836949 | H41: =(((($B$5*(1+H$38))*$B41+($B$5*(1+H$38))*$B$8-$B$9-(($B$12+0/2)*($B$10+0)))-MAX((($B$5*(1+H$38))*$B41+($B$5*(1+H$38))*$B$8-$B$9-(($B$12+0/2)*($B$10+0))),0)*$B$11)+$B$9+(($B$12+0/2)*($B$10+0)))/((($B$12+0/2)*($B$10+0))+$B$13) -> 1.2251591
A42: 0 | B42: =$B$7+A42 -> 0.52 | C42: =(((($B$5*(1+C$38))*$B42+($B$5*(1+C$38))*$B$8-$B$9-(($B$12+0/2)*($B$10+0)))-MAX((($B$5*(1+C$38))*$B42+($B$5*(1+C$38))*$B$8-$B$9-(($B$12+0/2)*($B$10+0))),0)*$B$11)+$B$9+(($B$12+0/2)*($B$10+0)))/((($B$12+0/2)*($B$10+0))+$B$13) -> 1.0547749 | D42: =(((($B$5*(1+D$38))*$B42+($B$5*(1+D$38))*$B$8-$B$9-(($B$12+0/2)*($B$10+0)))-MAX((($B$5*(1+D$38))*$B42+($B$5*(1+D$38))*$B$8-$B$9-(($B$12+0/2)*($B$10+0))),0)*$B$11)+$B$9+(($B$12+0/2)*($B$10+0)))/((($B$12+0/2)*($B$10+0))+$B$13) -> 1.0982248 | E42: =(((($B$5*(1+E$38))*$B42+($B$5*(1+E$38))*$B$8-$B$9-(($B$12+0/2)*($B$10+0)))-MAX((($B$5*(1+E$38))*$B42+($B$5*(1+E$38))*$B$8-$B$9-(($B$12+0/2)*($B$10+0))),0)*$B$11)+$B$9+(($B$12+0/2)*($B$10+0)))/((($B$12+0/2)*($B$10+0))+$B$13) -> 1.1416748 | F42: =(((($B$5*(1+F$38))*$B42+($B$5*(1+F$38))*$B$8-$B$9-(($B$12+0/2)*($B$10+0)))-MAX((($B$5*(1+F$38))*$B42+($B$5*(1+F$38))*$B$8-$B$9-(($B$12+0/2)*($B$10+0))),0)*$B$11)+$B$9+(($B$12+0/2)*($B$10+0)))/((($B$12+0/2)*($B$10+0))+$B$13) -> 1.1851247 | G42: =(((($B$5*(1+G$38))*$B42+($B$5*(1+G$38))*$B$8-$B$9-(($B$12+0/2)*($B$10+0)))-MAX((($B$5*(1+G$38))*$B42+($B$5*(1+G$38))*$B$8-$B$9-(($B$12+0/2)*($B$10+0))),0)*$B$11)+$B$9+(($B$12+0/2)*($B$10+0)))/((($B$12+0/2)*($B$10+0))+$B$13) -> 1.2285747 | H42: =(((($B$5*(1+H$38))*$B42+($B$5*(1+H$38))*$B$8-$B$9-(($B$12+0/2)*($B$10+0)))-MAX((($B$5*(1+H$38))*$B42+($B$5*(1+H$38))*$B$8-$B$9-(($B$12+0/2)*($B$10+0))),0)*$B$11)+$B$9+(($B$12+0/2)*($B$10+0)))/((($B$12+0/2)*($B$10+0))+$B$13) -> 1.2720246
A43: 0.025 | B43: =$B$7+A43 -> 0.545 | C43: =(((($B$5*(1+C$38))*$B43+($B$5*(1+C$38))*$B$8-$B$9-(($B$12+0/2)*($B$10+0)))-MAX((($B$5*(1+C$38))*$B43+($B$5*(1+C$38))*$B$8-$B$9-(($B$12+0/2)*($B$10+0))),0)*$B$11)+$B$9+(($B$12+0/2)*($B$10+0)))/((($B$12+0/2)*($B$10+0))+$B$13) -> 1.0917113 | D43: =(((($B$5*(1+D$38))*$B43+($B$5*(1+D$38))*$B$8-$B$9-(($B$12+0/2)*($B$10+0)))-MAX((($B$5*(1+D$38))*$B43+($B$5*(1+D$38))*$B$8-$B$9-(($B$12+0/2)*($B$10+0))),0)*$B$11)+$B$9+(($B$12+0/2)*($B$10+0)))/((($B$12+0/2)*($B$10+0))+$B$13) -> 1.1371471 | E43: =(((($B$5*(1+E$38))*$B43+($B$5*(1+E$38))*$B$8-$B$9-(($B$12+0/2)*($B$10+0)))-MAX((($B$5*(1+E$38))*$B43+($B$5*(1+E$38))*$B$8-$B$9-(($B$12+0/2)*($B$10+0))),0)*$B$11)+$B$9+(($B$12+0/2)*($B$10+0)))/((($B$12+0/2)*($B$10+0))+$B$13) -> 1.1825829 | F43: =(((($B$5*(1+F$38))*$B43+($B$5*(1+F$38))*$B$8-$B$9-(($B$12+0/2)*($B$10+0)))-MAX((($B$5*(1+F$38))*$B43+($B$5*(1+F$38))*$B$8-$B$9-(($B$12+0/2)*($B$10+0))),0)*$B$11)+$B$9+(($B$12+0/2)*($B$10+0)))/((($B$12+0/2)*($B$10+0))+$B$13) -> 1.2280187 | G43: =(((($B$5*(1+G$38))*$B43+($B$5*(1+G$38))*$B$8-$B$9-(($B$12+0/2)*($B$10+0)))-MAX((($B$5*(1+G$38))*$B43+($B$5*(1+G$38))*$B$8-$B$9-(($B$12+0/2)*($B$10+0))),0)*$B$11)+$B$9+(($B$12+0/2)*($B$10+0)))/((($B$12+0/2)*($B$10+0))+$B$13) -> 1.2734544 | H43: =(((($B$5*(1+H$38))*$B43+($B$5*(1+H$38))*$B$8-$B$9-(($B$12+0/2)*($B$10+0)))-MAX((($B$5*(1+H$38))*$B43+($B$5*(1+H$38))*$B$8-$B$9-(($B$12+0/2)*($B$10+0))),0)*$B$11)+$B$9+(($B$12+0/2)*($B$10+0)))/((($B$12+0/2)*($B$10+0))+$B$13) -> 1.3188902
A44: 0.05 | B44: =$B$7+A44 -> 0.57 | C44: =(((($B$5*(1+C$38))*$B44+($B$5*(1+C$38))*$B$8-$B$9-(($B$12+0/2)*($B$10+0)))-MAX((($B$5*(1+C$38))*$B44+($B$5*(1+C$38))*$B$8-$B$9-(($B$12+0/2)*($B$10+0))),0)*$B$11)+$B$9+(($B$12+0/2)*($B$10+0)))/((($B$12+0/2)*($B$10+0))+$B$13) -> 1.1286477 | D44: =(((($B$5*(1+D$38))*$B44+($B$5*(1+D$38))*$B$8-$B$9-(($B$12+0/2)*($B$10+0)))-MAX((($B$5*(1+D$38))*$B44+($B$5*(1+D$38))*$B$8-$B$9-(($B$12+0/2)*($B$10+0))),0)*$B$11)+$B$9+(($B$12+0/2)*($B$10+0)))/((($B$12+0/2)*($B$10+0))+$B$13) -> 1.1760694 | E44: =(((($B$5*(1+E$38))*$B44+($B$5*(1+E$38))*$B$8-$B$9-(($B$12+0/2)*($B$10+0)))-MAX((($B$5*(1+E$38))*$B44+($B$5*(1+E$38))*$B$8-$B$9-(($B$12+0/2)*($B$10+0))),0)*$B$11)+$B$9+(($B$12+0/2)*($B$10+0)))/((($B$12+0/2)*($B$10+0))+$B$13) -> 1.223491 | F44: =(((($B$5*(1+F$38))*$B44+($B$5*(1+F$38))*$B$8-$B$9-(($B$12+0/2)*($B$10+0)))-MAX((($B$5*(1+F$38))*$B44+($B$5*(1+F$38))*$B$8-$B$9-(($B$12+0/2)*($B$10+0))),0)*$B$11)+$B$9+(($B$12+0/2)*($B$10+0)))/((($B$12+0/2)*($B$10+0))+$B$13) -> 1.2709126 | G44: =(((($B$5*(1+G$38))*$B44+($B$5*(1+G$38))*$B$8-$B$9-(($B$12+0/2)*($B$10+0)))-MAX((($B$5*(1+G$38))*$B44+($B$5*(1+G$38))*$B$8-$B$9-(($B$12+0/2)*($B$10+0))),0)*$B$11)+$B$9+(($B$12+0/2)*($B$10+0)))/((($B$12+0/2)*($B$10+0))+$B$13) -> 1.3183342 | H44: =(((($B$5*(1+H$38))*$B44+($B$5*(1+H$38))*$B$8-$B$9-(($B$12+0/2)*($B$10+0)))-MAX((($B$5*(1+H$38))*$B44+($B$5*(1+H$38))*$B$8-$B$9-(($B$12+0/2)*($B$10+0))),0)*$B$11)+$B$9+(($B$12+0/2)*($B$10+0)))/((($B$12+0/2)*($B$10+0))+$B$13) -> 1.3657558
A47: 3. ICR (x): EBITDA margin vs interest-rate change
A48: Rows: EBITDA margin | Columns: Interest rate | B48: Δ vs base → | C48: -0.01 | D48: -0.005 | E48: 0 | F48: 0.005 | G48: 0.01 | H48: 0.02
B49: Level → | C49: =$B$10+C48 -> 0.076 | D49: =$B$10+D48 -> 0.081 | E49: =$B$10+E48 -> 0.086 | F49: =$B$10+F48 -> 0.091 | G49: =$B$10+G48 -> 0.096 | H49: =$B$10+H48 -> 0.106
A50: -0.1 | B50: =$B$7+A50 -> 0.42 | C50: =((($B$5*(1+$B$6))*$B50+($B$5*(1+$B$6))*$B$8-$B$9-(($B$12+0/2)*($B$10+C$48)))+(($B$12+0/2)*($B$10+C$48)))/(($B$12+0/2)*($B$10+C$48)) -> 1.7560766 | D50: =((($B$5*(1+$B$6))*$B50+($B$5*(1+$B$6))*$B$8-$B$9-(($B$12+0/2)*($B$10+D$48)))+(($B$12+0/2)*($B$10+D$48)))/(($B$12+0/2)*($B$10+D$48)) -> 1.6476768 | E50: =((($B$5*(1+$B$6))*$B50+($B$5*(1+$B$6))*$B$8-$B$9-(($B$12+0/2)*($B$10+E$48)))+(($B$12+0/2)*($B$10+E$48)))/(($B$12+0/2)*($B$10+E$48)) -> 1.5518816 | F50: =((($B$5*(1+$B$6))*$B50+($B$5*(1+$B$6))*$B$8-$B$9-(($B$12+0/2)*($B$10+F$48)))+(($B$12+0/2)*($B$10+F$48)))/(($B$12+0/2)*($B$10+F$48)) -> 1.4666134 | G50: =((($B$5*(1+$B$6))*$B50+($B$5*(1+$B$6))*$B$8-$B$9-(($B$12+0/2)*($B$10+G$48)))+(($B$12+0/2)*($B$10+G$48)))/(($B$12+0/2)*($B$10+G$48)) -> 1.3902273 | H50: =((($B$5*(1+$B$6))*$B50+($B$5*(1+$B$6))*$B$8-$B$9-(($B$12+0/2)*($B$10+H$48)))+(($B$12+0/2)*($B$10+H$48)))/(($B$12+0/2)*($B$10+H$48)) -> 1.2590738
A51: -0.05 | B51: =$B$7+A51 -> 0.47 | C51: =((($B$5*(1+$B$6))*$B51+($B$5*(1+$B$6))*$B$8-$B$9-(($B$12+0/2)*($B$10+C$48)))+(($B$12+0/2)*($B$10+C$48)))/(($B$12+0/2)*($B$10+C$48)) -> 2.0357945 | D51: =((($B$5*(1+$B$6))*$B51+($B$5*(1+$B$6))*$B$8-$B$9-(($B$12+0/2)*($B$10+D$48)))+(($B$12+0/2)*($B$10+D$48)))/(($B$12+0/2)*($B$10+D$48)) -> 1.9101282 | E51: =((($B$5*(1+$B$6))*$B51+($B$5*(1+$B$6))*$B$8-$B$9-(($B$12+0/2)*($B$10+E$48)))+(($B$12+0/2)*($B$10+E$48)))/(($B$12+0/2)*($B$10+E$48)) -> 1.7990742 | F51: =((($B$5*(1+$B$6))*$B51+($B$5*(1+$B$6))*$B$8-$B$9-(($B$12+0/2)*($B$10+F$48)))+(($B$12+0/2)*($B$10+F$48)))/(($B$12+0/2)*($B$10+F$48)) -> 1.700224 | G51: =((($B$5*(1+$B$6))*$B51+($B$5*(1+$B$6))*$B$8-$B$9-(($B$12+0/2)*($B$10+G$48)))+(($B$12+0/2)*($B$10+G$48)))/(($B$12+0/2)*($B$10+G$48)) -> 1.6116707 | H51: =((($B$5*(1+$B$6))*$B51+($B$5*(1+$B$6))*$B$8-$B$9-(($B$12+0/2)*($B$10+H$48)))+(($B$12+0/2)*($B$10+H$48)))/(($B$12+0/2)*($B$10+H$48)) -> 1.4596263
A52: -0.025 | B52: =$B$7+A52 -> 0.495 | C52: =((($B$5*(1+$B$6))*$B52+($B$5*(1+$B$6))*$B$8-$B$9-(($B$12+0/2)*($B$10+C$48)))+(($B$12+0/2)*($B$10+C$48)))/(($B$12+0/2)*($B$10+C$48)) -> 2.1756535 | D52: =((($B$5*(1+$B$6))*$B52+($B$5*(1+$B$6))*$B$8-$B$9-(($B$12+0/2)*($B$10+D$48)))+(($B$12+0/2)*($B$10+D$48)))/(($B$12+0/2)*($B$10+D$48)) -> 2.0413539 | E52: =((($B$5*(1+$B$6))*$B52+($B$5*(1+$B$6))*$B$8-$B$9-(($B$12+0/2)*($B$10+E$48)))+(($B$12+0/2)*($B$10+E$48)))/(($B$12+0/2)*($B$10+E$48)) -> 1.9226705 | F52: =((($B$5*(1+$B$6))*$B52+($B$5*(1+$B$6))*$B$8-$B$9-(($B$12+0/2)*($B$10+F$48)))+(($B$12+0/2)*($B$10+F$48)))/(($B$12+0/2)*($B$10+F$48)) -> 1.8170293 | G52: =((($B$5*(1+$B$6))*$B52+($B$5*(1+$B$6))*$B$8-$B$9-(($B$12+0/2)*($B$10+G$48)))+(($B$12+0/2)*($B$10+G$48)))/(($B$12+0/2)*($B$10+G$48)) -> 1.7223923 | H52: =((($B$5*(1+$B$6))*$B52+($B$5*(1+$B$6))*$B$8-$B$9-(($B$12+0/2)*($B$10+H$48)))+(($B$12+0/2)*($B$10+H$48)))/(($B$12+0/2)*($B$10+H$48)) -> 1.5599025
A53: 0 | B53: =$B$7+A53 -> 0.52 | C53: =((($B$5*(1+$B$6))*$B53+($B$5*(1+$B$6))*$B$8-$B$9-(($B$12+0/2)*($B$10+C$48)))+(($B$12+0/2)*($B$10+C$48)))/(($B$12+0/2)*($B$10+C$48)) -> 2.3155124 | D53: =((($B$5*(1+$B$6))*$B53+($B$5*(1+$B$6))*$B$8-$B$9-(($B$12+0/2)*($B$10+D$48)))+(($B$12+0/2)*($B$10+D$48)))/(($B$12+0/2)*($B$10+D$48)) -> 2.1725796 | E53: =((($B$5*(1+$B$6))*$B53+($B$5*(1+$B$6))*$B$8-$B$9-(($B$12+0/2)*($B$10+E$48)))+(($B$12+0/2)*($B$10+E$48)))/(($B$12+0/2)*($B$10+E$48)) -> 2.0462668 | F53: =((($B$5*(1+$B$6))*$B53+($B$5*(1+$B$6))*$B$8-$B$9-(($B$12+0/2)*($B$10+F$48)))+(($B$12+0/2)*($B$10+F$48)))/(($B$12+0/2)*($B$10+F$48)) -> 1.9338346 | G53: =((($B$5*(1+$B$6))*$B53+($B$5*(1+$B$6))*$B$8-$B$9-(($B$12+0/2)*($B$10+G$48)))+(($B$12+0/2)*($B$10+G$48)))/(($B$12+0/2)*($B$10+G$48)) -> 1.833114 | H53: =((($B$5*(1+$B$6))*$B53+($B$5*(1+$B$6))*$B$8-$B$9-(($B$12+0/2)*($B$10+H$48)))+(($B$12+0/2)*($B$10+H$48)))/(($B$12+0/2)*($B$10+H$48)) -> 1.6601787
A54: 0.025 | B54: =$B$7+A54 -> 0.545 | C54: =((($B$5*(1+$B$6))*$B54+($B$5*(1+$B$6))*$B$8-$B$9-(($B$12+0/2)*($B$10+C$48)))+(($B$12+0/2)*($B$10+C$48)))/(($B$12+0/2)*($B$10+C$48)) -> 2.4553714 | D54: =((($B$5*(1+$B$6))*$B54+($B$5*(1+$B$6))*$B$8-$B$9-(($B$12+0/2)*($B$10+D$48)))+(($B$12+0/2)*($B$10+D$48)))/(($B$12+0/2)*($B$10+D$48)) -> 2.3038053 | E54: =((($B$5*(1+$B$6))*$B54+($B$5*(1+$B$6))*$B$8-$B$9-(($B$12+0/2)*($B$10+E$48)))+(($B$12+0/2)*($B$10+E$48)))/(($B$12+0/2)*($B$10+E$48)) -> 2.1698631 | F54: =((($B$5*(1+$B$6))*$B54+($B$5*(1+$B$6))*$B$8-$B$9-(($B$12+0/2)*($B$10+F$48)))+(($B$12+0/2)*($B$10+F$48)))/(($B$12+0/2)*($B$10+F$48)) -> 2.0506399 | G54: =((($B$5*(1+$B$6))*$B54+($B$5*(1+$B$6))*$B$8-$B$9-(($B$12+0/2)*($B$10+G$48)))+(($B$12+0/2)*($B$10+G$48)))/(($B$12+0/2)*($B$10+G$48)) -> 1.9438357 | H54: =((($B$5*(1+$B$6))*$B54+($B$5*(1+$B$6))*$B$8-$B$9-(($B$12+0/2)*($B$10+H$48)))+(($B$12+0/2)*($B$10+H$48)))/(($B$12+0/2)*($B$10+H$48)) -> 1.760455
A55: 0.05 | B55: =$B$7+A55 -> 0.57 | C55: =((($B$5*(1+$B$6))*$B55+($B$5*(1+$B$6))*$B$8-$B$9-(($B$12+0/2)*($B$10+C$48)))+(($B$12+0/2)*($B$10+C$48)))/(($B$12+0/2)*($B$10+C$48)) -> 2.5952304 | D55: =((($B$5*(1+$B$6))*$B55+($B$5*(1+$B$6))*$B$8-$B$9-(($B$12+0/2)*($B$10+D$48)))+(($B$12+0/2)*($B$10+D$48)))/(($B$12+0/2)*($B$10+D$48)) -> 2.435031 | E55: =((($B$5*(1+$B$6))*$B55+($B$5*(1+$B$6))*$B$8-$B$9-(($B$12+0/2)*($B$10+E$48)))+(($B$12+0/2)*($B$10+E$48)))/(($B$12+0/2)*($B$10+E$48)) -> 2.2934594 | F55: =((($B$5*(1+$B$6))*$B55+($B$5*(1+$B$6))*$B$8-$B$9-(($B$12+0/2)*($B$10+F$48)))+(($B$12+0/2)*($B$10+F$48)))/(($B$12+0/2)*($B$10+F$48)) -> 2.1674452 | G55: =((($B$5*(1+$B$6))*$B55+($B$5*(1+$B$6))*$B$8-$B$9-(($B$12+0/2)*($B$10+G$48)))+(($B$12+0/2)*($B$10+G$48)))/(($B$12+0/2)*($B$10+G$48)) -> 2.0545574 | H55: =((($B$5*(1+$B$6))*$B55+($B$5*(1+$B$6))*$B$8-$B$9-(($B$12+0/2)*($B$10+H$48)))+(($B$12+0/2)*($B$10+H$48)))/(($B$12+0/2)*($B$10+H$48)) -> 1.8607312
A58: 4. TOL / TNW (x): additional borrowing vs revenue growth
A59: Rows: Additional borrowing (₹ cr) | Columns: Revenue growth | B59: Δ vs base → | C59: -0.15 | D59: -0.1 | E59: -0.05 | F59: 0 | G59: 0.05 | H59: 0.1
B60: Level → | C60: =$B$6+C59 -> -0.07 | D60: =$B$6+D59 -> -0.02 | E60: =$B$6+E59 -> 0.03 | F60: =$B$6+F59 -> 0.08 | G60: =$B$6+G59 -> 0.13 | H60: =$B$6+H59 -> 0.18
A61: 0 | B61: =A61 -> 0 | C61: =IF(($B$15+(((($B$5*(1+C$60))*$B$7+($B$5*(1+C$60))*$B$8-$B$9-(($B$12+$B61/2)*($B$10+0)))-MAX((($B$5*(1+C$60))*$B$7+($B$5*(1+C$60))*$B$8-$B$9-(($B$12+$B61/2)*($B$10+0))),0)*$B$11)-$B$18)*(1-$B$16)-Inputs!$B$6*$B$17)>0,($B$14+$B61)/($B$15+(((($B$5*(1+C$60))*$B$7+($B$5*(1+C$60))*$B$8-$B$9-(($B$12+$B61/2)*($B$10+0)))-MAX((($B$5*(1+C$60))*$B$7+($B$5*(1+C$60))*$B$8-$B$9-(($B$12+$B61/2)*($B$10+0))),0)*$B$11)-$B$18)*(1-$B$16)-Inputs!$B$6*$B$17),"n.m.") -> 1.4816698 | D61: =IF(($B$15+(((($B$5*(1+D$60))*$B$7+($B$5*(1+D$60))*$B$8-$B$9-(($B$12+$B61/2)*($B$10+0)))-MAX((($B$5*(1+D$60))*$B$7+($B$5*(1+D$60))*$B$8-$B$9-(($B$12+$B61/2)*($B$10+0))),0)*$B$11)-$B$18)*(1-$B$16)-Inputs!$B$6*$B$17)>0,($B$14+$B61)/($B$15+(((($B$5*(1+D$60))*$B$7+($B$5*(1+D$60))*$B$8-$B$9-(($B$12+$B61/2)*($B$10+0)))-MAX((($B$5*(1+D$60))*$B$7+($B$5*(1+D$60))*$B$8-$B$9-(($B$12+$B61/2)*($B$10+0))),0)*$B$11)-$B$18)*(1-$B$16)-Inputs!$B$6*$B$17),"n.m.") -> 1.4731874 | E61: =IF(($B$15+(((($B$5*(1+E$60))*$B$7+($B$5*(1+E$60))*$B$8-$B$9-(($B$12+$B61/2)*($B$10+0)))-MAX((($B$5*(1+E$60))*$B$7+($B$5*(1+E$60))*$B$8-$B$9-(($B$12+$B61/2)*($B$10+0))),0)*$B$11)-$B$18)*(1-$B$16)-Inputs!$B$6*$B$17)>0,($B$14+$B61)/($B$15+(((($B$5*(1+E$60))*$B$7+($B$5*(1+E$60))*$B$8-$B$9-(($B$12+$B61/2)*($B$10+0)))-MAX((($B$5*(1+E$60))*$B$7+($B$5*(1+E$60))*$B$8-$B$9-(($B$12+$B61/2)*($B$10+0))),0)*$B$11)-$B$18)*(1-$B$16)-Inputs!$B$6*$B$17),"n.m.") -> 1.4648014 | F61: =IF(($B$15+(((($B$5*(1+F$60))*$B$7+($B$5*(1+F$60))*$B$8-$B$9-(($B$12+$B61/2)*($B$10+0)))-MAX((($B$5*(1+F$60))*$B$7+($B$5*(1+F$60))*$B$8-$B$9-(($B$12+$B61/2)*($B$10+0))),0)*$B$11)-$B$18)*(1-$B$16)-Inputs!$B$6*$B$17)>0,($B$14+$B61)/($B$15+(((($B$5*(1+F$60))*$B$7+($B$5*(1+F$60))*$B$8-$B$9-(($B$12+$B61/2)*($B$10+0)))-MAX((($B$5*(1+F$60))*$B$7+($B$5*(1+F$60))*$B$8-$B$9-(($B$12+$B61/2)*($B$10+0))),0)*$B$11)-$B$18)*(1-$B$16)-Inputs!$B$6*$B$17),"n.m.") -> 1.4565105 | G61: =IF(($B$15+(((($B$5*(1+G$60))*$B$7+($B$5*(1+G$60))*$B$8-$B$9-(($B$12+$B61/2)*($B$10+0)))-MAX((($B$5*(1+G$60))*$B$7+($B$5*(1+G$60))*$B$8-$B$9-(($B$12+$B61/2)*($B$10+0))),0)*$B$11)-$B$18)*(1-$B$16)-Inputs!$B$6*$B$17)>0,($B$14+$B61)/($B$15+(((($B$5*(1+G$60))*$B$7+($B$5*(1+G$60))*$B$8-$B$9-(($B$12+$B61/2)*($B$10+0)))-MAX((($B$5*(1+G$60))*$B$7+($B$5*(1+G$60))*$B$8-$B$9-(($B$12+$B61/2)*($B$10+0))),0)*$B$11)-$B$18)*(1-$B$16)-Inputs!$B$6*$B$17),"n.m.") -> 1.4483128 | H61: =IF(($B$15+(((($B$5*(1+H$60))*$B$7+($B$5*(1+H$60))*$B$8-$B$9-(($B$12+$B61/2)*($B$10+0)))-MAX((($B$5*(1+H$60))*$B$7+($B$5*(1+H$60))*$B$8-$B$9-(($B$12+$B61/2)*($B$10+0))),0)*$B$11)-$B$18)*(1-$B$16)-Inputs!$B$6*$B$17)>0,($B$14+$B61)/($B$15+(((($B$5*(1+H$60))*$B$7+($B$5*(1+H$60))*$B$8-$B$9-(($B$12+$B61/2)*($B$10+0)))-MAX((($B$5*(1+H$60))*$B$7+($B$5*(1+H$60))*$B$8-$B$9-(($B$12+$B61/2)*($B$10+0))),0)*$B$11)-$B$18)*(1-$B$16)-Inputs!$B$6*$B$17),"n.m.") -> 1.4402069
A62: 1000 | B62: =A62 -> 1000 | C62: =IF(($B$15+(((($B$5*(1+C$60))*$B$7+($B$5*(1+C$60))*$B$8-$B$9-(($B$12+$B62/2)*($B$10+0)))-MAX((($B$5*(1+C$60))*$B$7+($B$5*(1+C$60))*$B$8-$B$9-(($B$12+$B62/2)*($B$10+0))),0)*$B$11)-$B$18)*(1-$B$16)-Inputs!$B$6*$B$17)>0,($B$14+$B62)/($B$15+(((($B$5*(1+C$60))*$B$7+($B$5*(1+C$60))*$B$8-$B$9-(($B$12+$B62/2)*($B$10+0)))-MAX((($B$5*(1+C$60))*$B$7+($B$5*(1+C$60))*$B$8-$B$9-(($B$12+$B62/2)*($B$10+0))),0)*$B$11)-$B$18)*(1-$B$16)-Inputs!$B$6*$B$17),"n.m.") -> 1.5297436 | D62: =IF(($B$15+(((($B$5*(1+D$60))*$B$7+($B$5*(1+D$60))*$B$8-$B$9-(($B$12+$B62/2)*($B$10+0)))-MAX((($B$5*(1+D$60))*$B$7+($B$5*(1+D$60))*$B$8-$B$9-(($B$12+$B62/2)*($B$10+0))),0)*$B$11)-$B$18)*(1-$B$16)-Inputs!$B$6*$B$17)>0,($B$14+$B62)/($B$15+(((($B$5*(1+D$60))*$B$7+($B$5*(1+D$60))*$B$8-$B$9-(($B$12+$B62/2)*($B$10+0)))-MAX((($B$5*(1+D$60))*$B$7+($B$5*(1+D$60))*$B$8-$B$9-(($B$12+$B62/2)*($B$10+0))),0)*$B$11)-$B$18)*(1-$B$16)-Inputs!$B$6*$B$17),"n.m.") -> 1.5209756 | E62: =IF(($B$15+(((($B$5*(1+E$60))*$B$7+($B$5*(1+E$60))*$B$8-$B$9-(($B$12+$B62/2)*($B$10+0)))-MAX((($B$5*(1+E$60))*$B$7+($B$5*(1+E$60))*$B$8-$B$9-(($B$12+$B62/2)*($B$10+0))),0)*$B$11)-$B$18)*(1-$B$16)-Inputs!$B$6*$B$17)>0,($B$14+$B62)/($B$15+(((($B$5*(1+E$60))*$B$7+($B$5*(1+E$60))*$B$8-$B$9-(($B$12+$B62/2)*($B$10+0)))-MAX((($B$5*(1+E$60))*$B$7+($B$5*(1+E$60))*$B$8-$B$9-(($B$12+$B62/2)*($B$10+0))),0)*$B$11)-$B$18)*(1-$B$16)-Inputs!$B$6*$B$17),"n.m.") -> 1.5123075 | F62: =IF(($B$15+(((($B$5*(1+F$60))*$B$7+($B$5*(1+F$60))*$B$8-$B$9-(($B$12+$B62/2)*($B$10+0)))-MAX((($B$5*(1+F$60))*$B$7+($B$5*(1+F$60))*$B$8-$B$9-(($B$12+$B62/2)*($B$10+0))),0)*$B$11)-$B$18)*(1-$B$16)-Inputs!$B$6*$B$17)>0,($B$14+$B62)/($B$15+(((($B$5*(1+F$60))*$B$7+($B$5*(1+F$60))*$B$8-$B$9-(($B$12+$B62/2)*($B$10+0)))-MAX((($B$5*(1+F$60))*$B$7+($B$5*(1+F$60))*$B$8-$B$9-(($B$12+$B62/2)*($B$10+0))),0)*$B$11)-$B$18)*(1-$B$16)-Inputs!$B$6*$B$17),"n.m.") -> 1.5037376 | G62: =IF(($B$15+(((($B$5*(1+G$60))*$B$7+($B$5*(1+G$60))*$B$8-$B$9-(($B$12+$B62/2)*($B$10+0)))-MAX((($B$5*(1+G$60))*$B$7+($B$5*(1+G$60))*$B$8-$B$9-(($B$12+$B62/2)*($B$10+0))),0)*$B$11)-$B$18)*(1-$B$16)-Inputs!$B$6*$B$17)>0,($B$14+$B62)/($B$15+(((($B$5*(1+G$60))*$B$7+($B$5*(1+G$60))*$B$8-$B$9-(($B$12+$B62/2)*($B$10+0)))-MAX((($B$5*(1+G$60))*$B$7+($B$5*(1+G$60))*$B$8-$B$9-(($B$12+$B62/2)*($B$10+0))),0)*$B$11)-$B$18)*(1-$B$16)-Inputs!$B$6*$B$17),"n.m.") -> 1.4952644 | H62: =IF(($B$15+(((($B$5*(1+H$60))*$B$7+($B$5*(1+H$60))*$B$8-$B$9-(($B$12+$B62/2)*($B$10+0)))-MAX((($B$5*(1+H$60))*$B$7+($B$5*(1+H$60))*$B$8-$B$9-(($B$12+$B62/2)*($B$10+0))),0)*$B$11)-$B$18)*(1-$B$16)-Inputs!$B$6*$B$17)>0,($B$14+$B62)/($B$15+(((($B$5*(1+H$60))*$B$7+($B$5*(1+H$60))*$B$8-$B$9-(($B$12+$B62/2)*($B$10+0)))-MAX((($B$5*(1+H$60))*$B$7+($B$5*(1+H$60))*$B$8-$B$9-(($B$12+$B62/2)*($B$10+0))),0)*$B$11)-$B$18)*(1-$B$16)-Inputs!$B$6*$B$17),"n.m.") -> 1.486886
A63: 2000 | B63: =A63 -> 2000 | C63: =IF(($B$15+(((($B$5*(1+C$60))*$B$7+($B$5*(1+C$60))*$B$8-$B$9-(($B$12+$B63/2)*($B$10+0)))-MAX((($B$5*(1+C$60))*$B$7+($B$5*(1+C$60))*$B$8-$B$9-(($B$12+$B63/2)*($B$10+0))),0)*$B$11)-$B$18)*(1-$B$16)-Inputs!$B$6*$B$17)>0,($B$14+$B63)/($B$15+(((($B$5*(1+C$60))*$B$7+($B$5*(1+C$60))*$B$8-$B$9-(($B$12+$B63/2)*($B$10+0)))-MAX((($B$5*(1+C$60))*$B$7+($B$5*(1+C$60))*$B$8-$B$9-(($B$12+$B63/2)*($B$10+0))),0)*$B$11)-$B$18)*(1-$B$16)-Inputs!$B$6*$B$17),"n.m.") -> 1.5779314 | D63: =IF(($B$15+(((($B$5*(1+D$60))*$B$7+($B$5*(1+D$60))*$B$8-$B$9-(($B$12+$B63/2)*($B$10+0)))-MAX((($B$5*(1+D$60))*$B$7+($B$5*(1+D$60))*$B$8-$B$9-(($B$12+$B63/2)*($B$10+0))),0)*$B$11)-$B$18)*(1-$B$16)-Inputs!$B$6*$B$17)>0,($B$14+$B63)/($B$15+(((($B$5*(1+D$60))*$B$7+($B$5*(1+D$60))*$B$8-$B$9-(($B$12+$B63/2)*($B$10+0)))-MAX((($B$5*(1+D$60))*$B$7+($B$5*(1+D$60))*$B$8-$B$9-(($B$12+$B63/2)*($B$10+0))),0)*$B$11)-$B$18)*(1-$B$16)-Inputs!$B$6*$B$17),"n.m.") -> 1.5688765 | E63: =IF(($B$15+(((($B$5*(1+E$60))*$B$7+($B$5*(1+E$60))*$B$8-$B$9-(($B$12+$B63/2)*($B$10+0)))-MAX((($B$5*(1+E$60))*$B$7+($B$5*(1+E$60))*$B$8-$B$9-(($B$12+$B63/2)*($B$10+0))),0)*$B$11)-$B$18)*(1-$B$16)-Inputs!$B$6*$B$17)>0,($B$14+$B63)/($B$15+(((($B$5*(1+E$60))*$B$7+($B$5*(1+E$60))*$B$8-$B$9-(($B$12+$B63/2)*($B$10+0)))-MAX((($B$5*(1+E$60))*$B$7+($B$5*(1+E$60))*$B$8-$B$9-(($B$12+$B63/2)*($B$10+0))),0)*$B$11)-$B$18)*(1-$B$16)-Inputs!$B$6*$B$17),"n.m.") -> 1.5599249 | F63: =IF(($B$15+(((($B$5*(1+F$60))*$B$7+($B$5*(1+F$60))*$B$8-$B$9-(($B$12+$B63/2)*($B$10+0)))-MAX((($B$5*(1+F$60))*$B$7+($B$5*(1+F$60))*$B$8-$B$9-(($B$12+$B63/2)*($B$10+0))),0)*$B$11)-$B$18)*(1-$B$16)-Inputs!$B$6*$B$17)>0,($B$14+$B63)/($B$15+(((($B$5*(1+F$60))*$B$7+($B$5*(1+F$60))*$B$8-$B$9-(($B$12+$B63/2)*($B$10+0)))-MAX((($B$5*(1+F$60))*$B$7+($B$5*(1+F$60))*$B$8-$B$9-(($B$12+$B63/2)*($B$10+0))),0)*$B$11)-$B$18)*(1-$B$16)-Inputs!$B$6*$B$17),"n.m.") -> 1.5510749 | G63: =IF(($B$15+(((($B$5*(1+G$60))*$B$7+($B$5*(1+G$60))*$B$8-$B$9-(($B$12+$B63/2)*($B$10+0)))-MAX((($B$5*(1+G$60))*$B$7+($B$5*(1+G$60))*$B$8-$B$9-(($B$12+$B63/2)*($B$10+0))),0)*$B$11)-$B$18)*(1-$B$16)-Inputs!$B$6*$B$17)>0,($B$14+$B63)/($B$15+(((($B$5*(1+G$60))*$B$7+($B$5*(1+G$60))*$B$8-$B$9-(($B$12+$B63/2)*($B$10+0)))-MAX((($B$5*(1+G$60))*$B$7+($B$5*(1+G$60))*$B$8-$B$9-(($B$12+$B63/2)*($B$10+0))),0)*$B$11)-$B$18)*(1-$B$16)-Inputs!$B$6*$B$17),"n.m.") -> 1.5423248 | H63: =IF(($B$15+(((($B$5*(1+H$60))*$B$7+($B$5*(1+H$60))*$B$8-$B$9-(($B$12+$B63/2)*($B$10+0)))-MAX((($B$5*(1+H$60))*$B$7+($B$5*(1+H$60))*$B$8-$B$9-(($B$12+$B63/2)*($B$10+0))),0)*$B$11)-$B$18)*(1-$B$16)-Inputs!$B$6*$B$17)>0,($B$14+$B63)/($B$15+(((($B$5*(1+H$60))*$B$7+($B$5*(1+H$60))*$B$8-$B$9-(($B$12+$B63/2)*($B$10+0)))-MAX((($B$5*(1+H$60))*$B$7+($B$5*(1+H$60))*$B$8-$B$9-(($B$12+$B63/2)*($B$10+0))),0)*$B$11)-$B$18)*(1-$B$16)-Inputs!$B$6*$B$17),"n.m.") -> 1.5336728
A64: 3000 | B64: =A64 -> 3000 | C64: =IF(($B$15+(((($B$5*(1+C$60))*$B$7+($B$5*(1+C$60))*$B$8-$B$9-(($B$12+$B64/2)*($B$10+0)))-MAX((($B$5*(1+C$60))*$B$7+($B$5*(1+C$60))*$B$8-$B$9-(($B$12+$B64/2)*($B$10+0))),0)*$B$11)-$B$18)*(1-$B$16)-Inputs!$B$6*$B$17)>0,($B$14+$B64)/($B$15+(((($B$5*(1+C$60))*$B$7+($B$5*(1+C$60))*$B$8-$B$9-(($B$12+$B64/2)*($B$10+0)))-MAX((($B$5*(1+C$60))*$B$7+($B$5*(1+C$60))*$B$8-$B$9-(($B$12+$B64/2)*($B$10+0))),0)*$B$11)-$B$18)*(1-$B$16)-Inputs!$B$6*$B$17),"n.m.") -> 1.6262337 | D64: =IF(($B$15+(((($B$5*(1+D$60))*$B$7+($B$5*(1+D$60))*$B$8-$B$9-(($B$12+$B64/2)*($B$10+0)))-MAX((($B$5*(1+D$60))*$B$7+($B$5*(1+D$60))*$B$8-$B$9-(($B$12+$B64/2)*($B$10+0))),0)*$B$11)-$B$18)*(1-$B$16)-Inputs!$B$6*$B$17)>0,($B$14+$B64)/($B$15+(((($B$5*(1+D$60))*$B$7+($B$5*(1+D$60))*$B$8-$B$9-(($B$12+$B64/2)*($B$10+0)))-MAX((($B$5*(1+D$60))*$B$7+($B$5*(1+D$60))*$B$8-$B$9-(($B$12+$B64/2)*($B$10+0))),0)*$B$11)-$B$18)*(1-$B$16)-Inputs!$B$6*$B$17),"n.m.") -> 1.6168906 | E64: =IF(($B$15+(((($B$5*(1+E$60))*$B$7+($B$5*(1+E$60))*$B$8-$B$9-(($B$12+$B64/2)*($B$10+0)))-MAX((($B$5*(1+E$60))*$B$7+($B$5*(1+E$60))*$B$8-$B$9-(($B$12+$B64/2)*($B$10+0))),0)*$B$11)-$B$18)*(1-$B$16)-Inputs!$B$6*$B$17)>0,($B$14+$B64)/($B$15+(((($B$5*(1+E$60))*$B$7+($B$5*(1+E$60))*$B$8-$B$9-(($B$12+$B64/2)*($B$10+0)))-MAX((($B$5*(1+E$60))*$B$7+($B$5*(1+E$60))*$B$8-$B$9-(($B$12+$B64/2)*($B$10+0))),0)*$B$11)-$B$18)*(1-$B$16)-Inputs!$B$6*$B$17),"n.m.") -> 1.6076542 | F64: =IF(($B$15+(((($B$5*(1+F$60))*$B$7+($B$5*(1+F$60))*$B$8-$B$9-(($B$12+$B64/2)*($B$10+0)))-MAX((($B$5*(1+F$60))*$B$7+($B$5*(1+F$60))*$B$8-$B$9-(($B$12+$B64/2)*($B$10+0))),0)*$B$11)-$B$18)*(1-$B$16)-Inputs!$B$6*$B$17)>0,($B$14+$B64)/($B$15+(((($B$5*(1+F$60))*$B$7+($B$5*(1+F$60))*$B$8-$B$9-(($B$12+$B64/2)*($B$10+0)))-MAX((($B$5*(1+F$60))*$B$7+($B$5*(1+F$60))*$B$8-$B$9-(($B$12+$B64/2)*($B$10+0))),0)*$B$11)-$B$18)*(1-$B$16)-Inputs!$B$6*$B$17),"n.m.") -> 1.5985228 | G64: =IF(($B$15+(((($B$5*(1+G$60))*$B$7+($B$5*(1+G$60))*$B$8-$B$9-(($B$12+$B64/2)*($B$10+0)))-MAX((($B$5*(1+G$60))*$B$7+($B$5*(1+G$60))*$B$8-$B$9-(($B$12+$B64/2)*($B$10+0))),0)*$B$11)-$B$18)*(1-$B$16)-Inputs!$B$6*$B$17)>0,($B$14+$B64)/($B$15+(((($B$5*(1+G$60))*$B$7+($B$5*(1+G$60))*$B$8-$B$9-(($B$12+$B64/2)*($B$10+0)))-MAX((($B$5*(1+G$60))*$B$7+($B$5*(1+G$60))*$B$8-$B$9-(($B$12+$B64/2)*($B$10+0))),0)*$B$11)-$B$18)*(1-$B$16)-Inputs!$B$6*$B$17),"n.m.") -> 1.5894945 | H64: =IF(($B$15+(((($B$5*(1+H$60))*$B$7+($B$5*(1+H$60))*$B$8-$B$9-(($B$12+$B64/2)*($B$10+0)))-MAX((($B$5*(1+H$60))*$B$7+($B$5*(1+H$60))*$B$8-$B$9-(($B$12+$B64/2)*($B$10+0))),0)*$B$11)-$B$18)*(1-$B$16)-Inputs!$B$6*$B$17)>0,($B$14+$B64)/($B$15+(((($B$5*(1+H$60))*$B$7+($B$5*(1+H$60))*$B$8-$B$9-(($B$12+$B64/2)*($B$10+0)))-MAX((($B$5*(1+H$60))*$B$7+($B$5*(1+H$60))*$B$8-$B$9-(($B$12+$B64/2)*($B$10+0))),0)*$B$11)-$B$18)*(1-$B$16)-Inputs!$B$6*$B$17),"n.m.") -> 1.5805677
A65: 5000 | B65: =A65 -> 5000 | C65: =IF(($B$15+(((($B$5*(1+C$60))*$B$7+($B$5*(1+C$60))*$B$8-$B$9-(($B$12+$B65/2)*($B$10+0)))-MAX((($B$5*(1+C$60))*$B$7+($B$5*(1+C$60))*$B$8-$B$9-(($B$12+$B65/2)*($B$10+0))),0)*$B$11)-$B$18)*(1-$B$16)-Inputs!$B$6*$B$17)>0,($B$14+$B65)/($B$15+(((($B$5*(1+C$60))*$B$7+($B$5*(1+C$60))*$B$8-$B$9-(($B$12+$B65/2)*($B$10+0)))-MAX((($B$5*(1+C$60))*$B$7+($B$5*(1+C$60))*$B$8-$B$9-(($B$12+$B65/2)*($B$10+0))),0)*$B$11)-$B$18)*(1-$B$16)-Inputs!$B$6*$B$17),"n.m.") -> 1.7231833 | D65: =IF(($B$15+(((($B$5*(1+D$60))*$B$7+($B$5*(1+D$60))*$B$8-$B$9-(($B$12+$B65/2)*($B$10+0)))-MAX((($B$5*(1+D$60))*$B$7+($B$5*(1+D$60))*$B$8-$B$9-(($B$12+$B65/2)*($B$10+0))),0)*$B$11)-$B$18)*(1-$B$16)-Inputs!$B$6*$B$17)>0,($B$14+$B65)/($B$15+(((($B$5*(1+D$60))*$B$7+($B$5*(1+D$60))*$B$8-$B$9-(($B$12+$B65/2)*($B$10+0)))-MAX((($B$5*(1+D$60))*$B$7+($B$5*(1+D$60))*$B$8-$B$9-(($B$12+$B65/2)*($B$10+0))),0)*$B$11)-$B$18)*(1-$B$16)-Inputs!$B$6*$B$17),"n.m.") -> 1.7132598 | E65: =IF(($B$15+(((($B$5*(1+E$60))*$B$7+($B$5*(1+E$60))*$B$8-$B$9-(($B$12+$B65/2)*($B$10+0)))-MAX((($B$5*(1+E$60))*$B$7+($B$5*(1+E$60))*$B$8-$B$9-(($B$12+$B65/2)*($B$10+0))),0)*$B$11)-$B$18)*(1-$B$16)-Inputs!$B$6*$B$17)>0,($B$14+$B65)/($B$15+(((($B$5*(1+E$60))*$B$7+($B$5*(1+E$60))*$B$8-$B$9-(($B$12+$B65/2)*($B$10+0)))-MAX((($B$5*(1+E$60))*$B$7+($B$5*(1+E$60))*$B$8-$B$9-(($B$12+$B65/2)*($B$10+0))),0)*$B$11)-$B$18)*(1-$B$16)-Inputs!$B$6*$B$17),"n.m.") -> 1.7034499 | F65: =IF(($B$15+(((($B$5*(1+F$60))*$B$7+($B$5*(1+F$60))*$B$8-$B$9-(($B$12+$B65/2)*($B$10+0)))-MAX((($B$5*(1+F$60))*$B$7+($B$5*(1+F$60))*$B$8-$B$9-(($B$12+$B65/2)*($B$10+0))),0)*$B$11)-$B$18)*(1-$B$16)-Inputs!$B$6*$B$17)>0,($B$14+$B65)/($B$15+(((($B$5*(1+F$60))*$B$7+($B$5*(1+F$60))*$B$8-$B$9-(($B$12+$B65/2)*($B$10+0)))-MAX((($B$5*(1+F$60))*$B$7+($B$5*(1+F$60))*$B$8-$B$9-(($B$12+$B65/2)*($B$10+0))),0)*$B$11)-$B$18)*(1-$B$16)-Inputs!$B$6*$B$17),"n.m.") -> 1.6937517 | G65: =IF(($B$15+(((($B$5*(1+G$60))*$B$7+($B$5*(1+G$60))*$B$8-$B$9-(($B$12+$B65/2)*($B$10+0)))-MAX((($B$5*(1+G$60))*$B$7+($B$5*(1+G$60))*$B$8-$B$9-(($B$12+$B65/2)*($B$10+0))),0)*$B$11)-$B$18)*(1-$B$16)-Inputs!$B$6*$B$17)>0,($B$14+$B65)/($B$15+(((($B$5*(1+G$60))*$B$7+($B$5*(1+G$60))*$B$8-$B$9-(($B$12+$B65/2)*($B$10+0)))-MAX((($B$5*(1+G$60))*$B$7+($B$5*(1+G$60))*$B$8-$B$9-(($B$12+$B65/2)*($B$10+0))),0)*$B$11)-$B$18)*(1-$B$16)-Inputs!$B$6*$B$17),"n.m.") -> 1.6841633 | H65: =IF(($B$15+(((($B$5*(1+H$60))*$B$7+($B$5*(1+H$60))*$B$8-$B$9-(($B$12+$B65/2)*($B$10+0)))-MAX((($B$5*(1+H$60))*$B$7+($B$5*(1+H$60))*$B$8-$B$9-(($B$12+$B65/2)*($B$10+0))),0)*$B$11)-$B$18)*(1-$B$16)-Inputs!$B$6*$B$17)>0,($B$14+$B65)/($B$15+(((($B$5*(1+H$60))*$B$7+($B$5*(1+H$60))*$B$8-$B$9-(($B$12+$B65/2)*($B$10+0)))-MAX((($B$5*(1+H$60))*$B$7+($B$5*(1+H$60))*$B$8-$B$9-(($B$12+$B65/2)*($B$10+0))),0)*$B$11)-$B$18)*(1-$B$16)-Inputs!$B$6*$B$17),"n.m.") -> 1.6746829
A66: 8000 | B66: =A66 -> 8000 | C66: =IF(($B$15+(((($B$5*(1+C$60))*$B$7+($B$5*(1+C$60))*$B$8-$B$9-(($B$12+$B66/2)*($B$10+0)))-MAX((($B$5*(1+C$60))*$B$7+($B$5*(1+C$60))*$B$8-$B$9-(($B$12+$B66/2)*($B$10+0))),0)*$B$11)-$B$18)*(1-$B$16)-Inputs!$B$6*$B$17)>0,($B$14+$B66)/($B$15+(((($B$5*(1+C$60))*$B$7+($B$5*(1+C$60))*$B$8-$B$9-(($B$12+$B66/2)*($B$10+0)))-MAX((($B$5*(1+C$60))*$B$7+($B$5*(1+C$60))*$B$8-$B$9-(($B$12+$B66/2)*($B$10+0))),0)*$B$11)-$B$18)*(1-$B$16)-Inputs!$B$6*$B$17),"n.m.") -> 1.8694766 | D66: =IF(($B$15+(((($B$5*(1+D$60))*$B$7+($B$5*(1+D$60))*$B$8-$B$9-(($B$12+$B66/2)*($B$10+0)))-MAX((($B$5*(1+D$60))*$B$7+($B$5*(1+D$60))*$B$8-$B$9-(($B$12+$B66/2)*($B$10+0))),0)*$B$11)-$B$18)*(1-$B$16)-Inputs!$B$6*$B$17)>0,($B$14+$B66)/($B$15+(((($B$5*(1+D$60))*$B$7+($B$5*(1+D$60))*$B$8-$B$9-(($B$12+$B66/2)*($B$10+0)))-MAX((($B$5*(1+D$60))*$B$7+($B$5*(1+D$60))*$B$8-$B$9-(($B$12+$B66/2)*($B$10+0))),0)*$B$11)-$B$18)*(1-$B$16)-Inputs!$B$6*$B$17),"n.m.") -> 1.8586723 | E66: =IF(($B$15+(((($B$5*(1+E$60))*$B$7+($B$5*(1+E$60))*$B$8-$B$9-(($B$12+$B66/2)*($B$10+0)))-MAX((($B$5*(1+E$60))*$B$7+($B$5*(1+E$60))*$B$8-$B$9-(($B$12+$B66/2)*($B$10+0))),0)*$B$11)-$B$18)*(1-$B$16)-Inputs!$B$6*$B$17)>0,($B$14+$B66)/($B$15+(((($B$5*(1+E$60))*$B$7+($B$5*(1+E$60))*$B$8-$B$9-(($B$12+$B66/2)*($B$10+0)))-MAX((($B$5*(1+E$60))*$B$7+($B$5*(1+E$60))*$B$8-$B$9-(($B$12+$B66/2)*($B$10+0))),0)*$B$11)-$B$18)*(1-$B$16)-Inputs!$B$6*$B$17),"n.m.") -> 1.8479921 | F66: =IF(($B$15+(((($B$5*(1+F$60))*$B$7+($B$5*(1+F$60))*$B$8-$B$9-(($B$12+$B66/2)*($B$10+0)))-MAX((($B$5*(1+F$60))*$B$7+($B$5*(1+F$60))*$B$8-$B$9-(($B$12+$B66/2)*($B$10+0))),0)*$B$11)-$B$18)*(1-$B$16)-Inputs!$B$6*$B$17)>0,($B$14+$B66)/($B$15+(((($B$5*(1+F$60))*$B$7+($B$5*(1+F$60))*$B$8-$B$9-(($B$12+$B66/2)*($B$10+0)))-MAX((($B$5*(1+F$60))*$B$7+($B$5*(1+F$60))*$B$8-$B$9-(($B$12+$B66/2)*($B$10+0))),0)*$B$11)-$B$18)*(1-$B$16)-Inputs!$B$6*$B$17),"n.m.") -> 1.8374339 | G66: =IF(($B$15+(((($B$5*(1+G$60))*$B$7+($B$5*(1+G$60))*$B$8-$B$9-(($B$12+$B66/2)*($B$10+0)))-MAX((($B$5*(1+G$60))*$B$7+($B$5*(1+G$60))*$B$8-$B$9-(($B$12+$B66/2)*($B$10+0))),0)*$B$11)-$B$18)*(1-$B$16)-Inputs!$B$6*$B$17)>0,($B$14+$B66)/($B$15+(((($B$5*(1+G$60))*$B$7+($B$5*(1+G$60))*$B$8-$B$9-(($B$12+$B66/2)*($B$10+0)))-MAX((($B$5*(1+G$60))*$B$7+($B$5*(1+G$60))*$B$8-$B$9-(($B$12+$B66/2)*($B$10+0))),0)*$B$11)-$B$18)*(1-$B$16)-Inputs!$B$6*$B$17),"n.m.") -> 1.8269957 | H66: =IF(($B$15+(((($B$5*(1+H$60))*$B$7+($B$5*(1+H$60))*$B$8-$B$9-(($B$12+$B66/2)*($B$10+0)))-MAX((($B$5*(1+H$60))*$B$7+($B$5*(1+H$60))*$B$8-$B$9-(($B$12+$B66/2)*($B$10+0))),0)*$B$11)-$B$18)*(1-$B$16)-Inputs!$B$6*$B$17)>0,($B$14+$B66)/($B$15+(((($B$5*(1+H$60))*$B$7+($B$5*(1+H$60))*$B$8-$B$9-(($B$12+$B66/2)*($B$10+0)))-MAX((($B$5*(1+H$60))*$B$7+($B$5*(1+H$60))*$B$8-$B$9-(($B$12+$B66/2)*($B$10+0))),0)*$B$11)-$B$18)*(1-$B$16)-Inputs!$B$6*$B$17),"n.m.") -> 1.8166754
A69: Green = meets the benchmark on the Inputs tab; red = breaches it. Benchmarks are illustrative — replace with sanction terms.
